Workbook

Sheet Readme
B2: Sources:
A3: 1) | B3: Babecký ·et al. (2012)
B4: https://www.google.com/url?sa=t&rct=j&q=&esrc=s&source=web&cd=&cad=rja&uact=8&ved=2ahUKEwjckO7um4KMAxWuS0EAHWTSJdEQFnoECBkQAQ&url=https%3A%2F%2Fwww.ecb.europa.eu%2Fpub%2Fpdf%2Fscpops%2Fecb.op194.pt.pdf&usg=AOvVaw2GNoBiPv8DEd_oW1DP2aoP&opi=89978449
B5: EU27 Crises Database created with the help of the ESCB Heads of Research Group
B6: Approved in June 2012
B8: This dataset has been used for the accompanying ECB working paper:
B9: Banking, Debt, and Currency Crises:
B10: Early Warning Indicators for Developed Countries
B12: Jan Babecký a, Tomáš Havránek a,b, Jakub Matějů a,c,
B13: Marek Rusnák a,b, Kateřina Šmídková a,b, and Bořek Vašíček a
A15: 2) | B15: Laeven and Valencia (2020)
B16: Systemic Banking Crises Database II
A18: 3) | B18: FX
B19: Raw data: https://fred.stlouisfed.org/series/CCUSMA02IEQ618N
B20: CCUSMA02IEQ618N
B21: Currency Conversions: US Dollar Exchange Rate: Average of Daily Rates: National Currency: USD for Ireland, Euro, Quarterly, Not Seasonally Adjusted
B23: In C_Properties/C2.Properties.R code
B24: we detrend the FX (IE/US dollars)
B25: Results exported in
B26: C_Properties\1.Crisis_events\fx_filtered.xlsx
B27: We extend the currency crisis period reported in Babecky ·et al. (2012), by taking the period where the FX trend continued decreasing yoy
A29: 4) | B29: Baron and Dieckelmann (2022)
B30: file:///\\Filescluster\shared\MPS\WORD\MPFS%20DEPT\Farah\Alternative_Gap\New_Model\Ruenstler_and_Vlekke_2018\C_Robustness_Checks\1.Early_warnings\Bank_crisis\Raw_data\Baron_Dieckelmann_Panics_and_bank_failures_database.xlsx
B31: Link https://www.quantfinhistory.org/banking-crises-database
B32: Baron, M., & Dieckelmann, D. (2022). Historical Banking Crises: A New Database and a Reassessment of their Incidence and Severity. In: Leveraged: The New Economics of Debt and Financial Fragility. University of Chicago Press, forthcoming.
B33: The Historical Banking Crises Database
B34: 42 countries, 1870-2019
B35: Banking crisis characteristics
B36: Banking panics and bank failures, 1870-2016
B38: Notes:
B39: Crisis_Babecky | D39: All the sources excluding Bank Eq. 30% decline.
B40: Crisis_Babecky_Baron | D40: All the sources excluding Bank Eq. 30% decline.
B41: Labels: just for the graphs produced in C2.Properties.R
B44: Farah Mugrabi

Sheet Crisis
A1: Date | B1: Crisis_Babecky | C1: Crisis_Babecky_Baron | D1: Reference | E1: Label
A2: 28491 | B2: =Crisis_construction!F3 -> 0 | C2: =Crisis_construction!G3 -> 0 | D2: =+Crisis_construction!I3 -> 0
A3: 28581 | B3: =Crisis_construction!F4 -> 0 | C3: =Crisis_construction!G4 -> 0 | D3: =+Crisis_construction!I4 -> 0
A4: 28672 | B4: =Crisis_construction!F5 -> 0 | C4: =Crisis_construction!G5 -> 0 | D4: =+Crisis_construction!I5 -> 0
A5: 28764 | B5: =Crisis_construction!F6 -> 0 | C5: =Crisis_construction!G6 -> 0 | D5: =+Crisis_construction!I6 -> 0
A6: 28856 | B6: =Crisis_construction!F7 -> 0 | C6: =Crisis_construction!G7 -> 0 | D6: =+Crisis_construction!I7 -> 0
A7: 28946 | B7: =Crisis_construction!F8 -> 0 | C7: =Crisis_construction!G8 -> 0 | D7: =+Crisis_construction!I8 -> 0
A8: 29037 | B8: =Crisis_construction!F9 -> 0 | C8: =Crisis_construction!G9 -> 0 | D8: =+Crisis_construction!I9 -> 0
A9: 29129 | B9: =Crisis_construction!F10 -> 0 | C9: =Crisis_construction!G10 -> 0 | D9: =+Crisis_construction!I10 -> 0
A10: 29221 | B10: =Crisis_construction!F11 -> 0 | C10: =Crisis_construction!G11 -> 0 | D10: =+Crisis_construction!I11 -> 0
A11: 29312 | B11: =Crisis_construction!F12 -> 0 | C11: =Crisis_construction!G12 -> 0 | D11: =+Crisis_construction!I12 -> 0
A12: 29403 | B12: =Crisis_construction!F13 -> 0 | C12: =Crisis_construction!G13 -> 0 | D12: =+Crisis_construction!I13 -> 0
A13: 29495 | B13: =Crisis_construction!F14 -> 0 | C13: =Crisis_construction!G14 -> 0 | D13: =+Crisis_construction!I14 -> 0
... A29: 30956 | B29: =Crisis_construction!F30 -> 0 | C29: =Crisis_construction!G30 -> 0 | D29: =+Crisis_construction!I30 -> 0
A30: 31048 | B30: =Crisis_construction!F31 -> 1 | C30: =Crisis_construction!G31 -> 1 | D30: =+Crisis_construction!I31 -> Babecky ·et al. (2012) - Currency crisis. | E30: 1
A31: 31138 | B31: =Crisis_construction!F32 -> 0 | C31: =Crisis_construction!G32 -> 0 | D31: =+Crisis_construction!I32 -> 0
A32: 31229 | B32: =Crisis_construction!F33 -> 1 | C32: =Crisis_construction!G33 -> 1 | D32: =+Crisis_construction!I33 -> FX (US/IE) substantial decline - Currency crisis. | E32: 0.9
A33: 31321 | B33: =Crisis_construction!F34 -> 1 | C33: =Crisis_construction!G34 -> 1 | D33: =+Crisis_construction!I34 -> 0
A34: 31413 | B34: =Crisis_construction!F35 -> 1 | C34: =Crisis_construction!G35 -> 1 | D34: =+Crisis_construction!I35 -> 0
A35: 31503 | B35: =Crisis_construction!F36 -> 1 | C35: =Crisis_construction!G36 -> 1 | D35: =+Crisis_construction!I36 -> 0
A36: 31594 | B36: =Crisis_construction!F37 -> 1 | C36: =Crisis_construction!G37 -> 1 | D36: =+Crisis_construction!I37 -> 0
A37: 31686 | B37: =Crisis_construction!F38 -> 1 | C37: =Crisis_construction!G38 -> 1 | D37: =+Crisis_construction!I38 -> 0
A38: 31778 | B38: =Crisis_construction!F39 -> 1 | C38: =Crisis_construction!G39 -> 1 | D38: =+Crisis_construction!I39 -> 0
A39: 31868 | B39: =Crisis_construction!F40 -> 1 | C39: =Crisis_construction!G40 -> 1 | D39: =+Crisis_construction!I40 -> 0
A40: 31959 | B40: =Crisis_construction!F41 -> 1 | C40: =Crisis_construction!G41 -> 1 | D40: =+Crisis_construction!I41 -> 0
A41: 32051 | B41: =Crisis_construction!F42 -> 1 | C41: =Crisis_construction!G42 -> 1 | D41: =+Crisis_construction!I42 -> 0
A42: 32143 | B42: =Crisis_construction!F43 -> 1 | C42: =Crisis_construction!G43 -> 1 | D42: =+Crisis_construction!I43 -> 0
A43: 32234 | B43: =Crisis_construction!F44 -> 1 | C43: =Crisis_construction!G44 -> 1 | D43: =+Crisis_construction!I44 -> 0
A44: 32325 | B44: =Crisis_construction!F45 -> 0 | C44: =Crisis_construction!G45 -> 0 | D44: =+Crisis_construction!I45 -> 0
... A49: 32782 | B49: =Crisis_construction!F50 -> 0 | C49: =Crisis_construction!G50 -> 0 | D49: =+Crisis_construction!I50 -> 0
A50: 32874 | B50: =Crisis_construction!F51 -> 0 | C50: =Crisis_construction!G51 -> 1 | D50: =+Crisis_construction!I51 -> Baron and Dieckelmann (2022) -Bank Eq. 30% decline. | E50: 0.8
A51: 32964 | B51: =Crisis_construction!F52 -> 0 | C51: =Crisis_construction!G52 -> 1 | D51: =+Crisis_construction!I52 -> 0
A52: 33055 | B52: =Crisis_construction!F53 -> 0 | C52: =Crisis_construction!G53 -> 1 | D52: =+Crisis_construction!I53 -> 0
A53: 33147 | B53: =Crisis_construction!F54 -> 0 | C53: =Crisis_construction!G54 -> 1 | D53: =+Crisis_construction!I54 -> 0
A54: 33239 | B54: =Crisis_construction!F55 -> 0 | C54: =Crisis_construction!G55 -> 0 | D54: =+Crisis_construction!I55 -> 0
A55: 33329 | B55: =Crisis_construction!F56 -> 0 | C55: =Crisis_construction!G56 -> 0 | D55: =+Crisis_construction!I56 -> 0
A56: 33420 | B56: =Crisis_construction!F57 -> 0 | C56: =Crisis_construction!G57 -> 0 | D56: =+Crisis_construction!I57 -> 0
A57: 33512 | B57: =Crisis_construction!F58 -> 0 | C57: =Crisis_construction!G58 -> 0 | D57: =+Crisis_construction!I58 -> 0
A58: 33604 | B58: =Crisis_construction!F59 -> 0 | C58: =Crisis_construction!G59 -> 0 | D58: =+Crisis_construction!I59 -> 0
A59: 33695 | B59: =Crisis_construction!F60 -> 0 | C59: =Crisis_construction!G60 -> 0 | D59: =+Crisis_construction!I60 -> 0
A60: 33786 | B60: =Crisis_construction!F61 -> 0 | C60: =Crisis_construction!G61 -> 0 | D60: =+Crisis_construction!I61 -> 0
A61: 33878 | B61: =Crisis_construction!F62 -> 0 | C61: =Crisis_construction!G62 -> 0 | D61: =+Crisis_construction!I62 -> 0
A62: 33970 | B62: =Crisis_construction!F63 -> 0 | C62: =Crisis_construction!G63 -> 0 | D62: =+Crisis_construction!I63 -> 0
... A121: 39356 | B121: =Crisis_construction!F122 -> 0 | C121: =Crisis_construction!G122 -> 0 | D121: =+Crisis_construction!I122 -> 0
A122: 39448 | B122: =Crisis_construction!F123 -> 1 | C122: =Crisis_construction!G123 -> 1 | D122: =+Crisis_construction!I123 -> Laeven and Valencia (2020) - Systemic Banking Crisis - Anglo Irish Bank failed and was nationalized in 2009. | E122: 0.7
A123: 39539 | B123: =Crisis_construction!F124 -> 1 | C123: =Crisis_construction!G124 -> 1 | D123: =+Crisis_construction!I124 -> 0
A124: 39630 | B124: =Crisis_construction!F125 -> 1 | C124: =Crisis_construction!G125 -> 1 | D124: =+Crisis_construction!I125 -> 0
A125: 39722 | B125: =Crisis_construction!F126 -> 1 | C125: =Crisis_construction!G126 -> 1 | D125: =+Crisis_construction!I126 -> 0
A126: 39814 | B126: =Crisis_construction!F127 -> 1 | C126: =Crisis_construction!G127 -> 1 | D126: =+Crisis_construction!I127 -> 0
A127: 39904 | B127: =Crisis_construction!F128 -> 1 | C127: =Crisis_construction!G128 -> 1 | D127: =+Crisis_construction!I128 -> 0
A128: 39995 | B128: =Crisis_construction!F129 -> 1 | C128: =Crisis_construction!G129 -> 1 | D128: =+Crisis_construction!I129 -> 0
A129: 40087 | B129: =Crisis_construction!F130 -> 1 | C129: =Crisis_construction!G130 -> 1 | D129: =+Crisis_construction!I130 -> 0
A130: 40179 | B130: =Crisis_construction!F131 -> 1 | C130: =Crisis_construction!G131 -> 1 | D130: =+Crisis_construction!I131 -> 0
A131: 40269 | B131: =Crisis_construction!F132 -> 1 | C131: =Crisis_construction!G132 -> 1 | D131: =+Crisis_construction!I132 -> 0
A132: 40360 | B132: =Crisis_construction!F133 -> 1 | C132: =Crisis_construction!G133 -> 1 | D132: =+Crisis_construction!I133 -> Laeven and Valencia (2020) - Systemic Banking Crisis -Bank of Ireland was bailed out and EBS Building Society was nationalized. | E132: 0.5
A133: 40452 | B133: =Crisis_construction!F134 -> 1 | C133: =Crisis_construction!G134 -> 1 | D133: =+Crisis_construction!I134 -> 0
A134: 40544 | B134: =Crisis_construction!F135 -> 1 | C134: =Crisis_construction!G135 -> 1 | D134: =+Crisis_construction!I135 -> 0
A135: 40634 | B135: =Crisis_construction!F136 -> 1 | C135: =Crisis_construction!G136 -> 1 | D135: =+Crisis_construction!I136 -> 0
A136: 40725 | B136: =Crisis_construction!F137 -> 1 | C136: =Crisis_construction!G137 -> 1 | D136: =+Crisis_construction!I137 -> 0
A137: 40817 | B137: =Crisis_construction!F138 -> 1 | C137: =Crisis_construction!G138 -> 1 | D137: =+Crisis_construction!I138 -> 0
A138: 40909 | B138: =Crisis_construction!F139 -> 1 | C138: =Crisis_construction!G139 -> 1 | D138: =+Crisis_construction!I139 -> 0
A139: 41000 | B139: =Crisis_construction!F140 -> 1 | C139: =Crisis_construction!G140 -> 1 | D139: =+Crisis_construction!I140 -> 0
A140: 41091 | B140: =Crisis_construction!F141 -> 1 | C140: =Crisis_construction!G141 -> 1 | D140: =+Crisis_construction!I141 -> 0
A141: 41183 | B141: =Crisis_construction!F142 -> 1 | C141: =Crisis_construction!G142 -> 1 | D141: =+Crisis_construction!I142 -> 0
A142: 41275 | B142: =Crisis_construction!F143 -> 0 | C142: =Crisis_construction!G143 -> 0 | D142: =+Crisis_construction!I143 -> 0
A143: 41365 | B143: =Crisis_construction!F144 -> 0 | C143: =Crisis_construction!G144 -> 0 | D143: =+Crisis_construction!I144 -> 0
A144: 41456 | B144: =Crisis_construction!F145 -> 0 | C144: =Crisis_construction!G145 -> 0 | D144: =+Crisis_construction!I145 -> 0
... A153: 42278 | B153: =Crisis_construction!F154 -> 0 | C153: =Crisis_construction!G154 -> 0 | D153: =+Crisis_construction!I154 -> 0
A154: 42370 | B154: =Crisis_construction!F155 -> 0 | C154: =Crisis_construction!G155 -> 1 | D154: =+Crisis_construction!I155 -> Baron and Dieckelmann (2022) -Bank Eq. 30% decline. | E154: 0.3
A155: 42461 | B155: =Crisis_construction!F156 -> 0 | C155: =Crisis_construction!G156 -> 1 | D155: =+Crisis_construction!I156 -> 0
A156: 42552 | B156: =Crisis_construction!F157 -> 0 | C156: =Crisis_construction!G157 -> 1 | D156: =+Crisis_construction!I157 -> 0
A157: 42644 | B157: =Crisis_construction!F158 -> 0 | C157: =Crisis_construction!G158 -> 1 | D157: =+Crisis_construction!I158 -> 0
A158: 42736 | B158: =Crisis_construction!F159 -> 0 | C158: =Crisis_construction!G159 -> 0 | D158: =+Crisis_construction!I159 -> 0
A159: 42826 | B159: =Crisis_construction!F160 -> 0 | C159: =Crisis_construction!G160 -> 0 | D159: =+Crisis_construction!I160 -> 0
A160: 42917 | B160: =Crisis_construction!F161 -> 0 | C160: =Crisis_construction!G161 -> 0 | D160: =+Crisis_construction!I161 -> 0
A161: 43009 | B161: =Crisis_construction!F162 -> 0 | C161: =Crisis_construction!G162 -> 0 | D161: =+Crisis_construction!I162 -> 0
A162: 43101 | B162: =Crisis_construction!F163 -> 0 | C162: =Crisis_construction!G163 -> 0 | D162: =+Crisis_construction!I163 -> 0
A163: 43191 | B163: =Crisis_construction!F164 -> 0 | C163: =Crisis_construction!G164 -> 0 | D163: =+Crisis_construction!I164 -> 0
A164: 43282 | B164: =Crisis_construction!F165 -> 0 | C164: =Crisis_construction!G165 -> 0 | D164: =+Crisis_construction!I165 -> 0
A165: 43374 | B165: =Crisis_construction!F166 -> 0 | C165: =Crisis_construction!G166 -> 0 | D165: =+Crisis_construction!I166 -> 0
A166: 43466 | B166: =Crisis_construction!F167 -> 0 | C166: =Crisis_construction!G167 -> 0 | D166: =+Crisis_construction!I167 -> 0
... A191: 45748 | B191: =Crisis_construction!F192 -> 0 | C191: =Crisis_construction!G192 -> 0 | D191: =+Crisis_construction!I192 -> 0

Sheet Crisis_construction
B1: Raw_sources
A2: Date | B2: Babecky ·et al. (2012) | C2: Laeven and Valencia (2020) | D2: FX | E2: Baron and Dieckelmann (2022) | F2: Crisis_Babecky | G2: Crisis_Babecky_Baron | I2: Reference
A3: 28491 | B3: ='Babecky ·et al. (2012)'!B34 -> 0 | D3: =FX!F2 -> 0 | E3: 0 | F3: =+IF(SUM(B3:D3)=0,0,1) -> 0 | G3: =+IF(SUM(B3:E3)=0,0,1) -> 0
A4: 28581 | B4: ='Babecky ·et al. (2012)'!B35 -> 0 | D4: =FX!F3 -> 0 | E4: 0 | F4: =+IF(SUM(B4:D4)=0,0,1) -> 0 | G4: =+IF(SUM(B4:E4)=0,0,1) -> 0
A5: 28672 | B5: ='Babecky ·et al. (2012)'!B36 -> 0 | D5: =FX!F4 -> 0 | E5: 0 | F5: =+IF(SUM(B5:D5)=0,0,1) -> 0 | G5: =+IF(SUM(B5:E5)=0,0,1) -> 0
A6: 28764 | B6: ='Babecky ·et al. (2012)'!B37 -> 0 | D6: =FX!F5 -> 0 | E6: 0 | F6: =+IF(SUM(B6:D6)=0,0,1) -> 0 | G6: =+IF(SUM(B6:E6)=0,0,1) -> 0
A7: 28856 | B7: ='Babecky ·et al. (2012)'!B38 -> 0 | D7: =FX!F6 -> 0 | E7: 0 | F7: =+IF(SUM(B7:D7)=0,0,1) -> 0 | G7: =+IF(SUM(B7:E7)=0,0,1) -> 0
A8: 28946 | B8: ='Babecky ·et al. (2012)'!B39 -> 0 | D8: =FX!F7 -> 0 | E8: 0 | F8: =+IF(SUM(B8:D8)=0,0,1) -> 0 | G8: =+IF(SUM(B8:E8)=0,0,1) -> 0
A9: 29037 | B9: ='Babecky ·et al. (2012)'!B40 -> 0 | D9: =FX!F8 -> 0 | E9: 0 | F9: =+IF(SUM(B9:D9)=0,0,1) -> 0 | G9: =+IF(SUM(B9:E9)=0,0,1) -> 0
A10: 29129 | B10: ='Babecky ·et al. (2012)'!B41 -> 0 | D10: =FX!F9 -> 0 | E10: 0 | F10: =+IF(SUM(B10:D10)=0,0,1) -> 0 | G10: =+IF(SUM(B10:E10)=0,0,1) -> 0
A11: 29221 | B11: ='Babecky ·et al. (2012)'!B42 -> 0 | D11: =FX!F10 -> 0 | E11: 0 | F11: =+IF(SUM(B11:D11)=0,0,1) -> 0 | G11: =+IF(SUM(B11:E11)=0,0,1) -> 0
A12: 29312 | B12: ='Babecky ·et al. (2012)'!B43 -> 0 | D12: =FX!F11 -> 0 | E12: 0 | F12: =+IF(SUM(B12:D12)=0,0,1) -> 0 | G12: =+IF(SUM(B12:E12)=0,0,1) -> 0
A13: 29403 | B13: ='Babecky ·et al. (2012)'!B44 -> 0 | D13: =FX!F12 -> 0 | E13: 0 | F13: =+IF(SUM(B13:D13)=0,0,1) -> 0 | G13: =+IF(SUM(B13:E13)=0,0,1) -> 0
A14: 29495 | B14: ='Babecky ·et al. (2012)'!B45 -> 0 | D14: =FX!F13 -> 0 | E14: 0 | F14: =+IF(SUM(B14:D14)=0,0,1) -> 0 | G14: =+IF(SUM(B14:E14)=0,0,1) -> 0
... A30: 30956 | B30: ='Babecky ·et al. (2012)'!B61 -> 0 | D30: =FX!F29 -> 0 | E30: 0 | F30: =+IF(SUM(B30:D30)=0,0,1) -> 0 | G30: =+IF(SUM(B30:E30)=0,0,1) -> 0
A31: 31048 | B31: ='Babecky ·et al. (2012)'!B62 -> 1 | D31: =FX!F30 -> 0 | E31: 0 | F31: =+IF(SUM(B31:D31)=0,0,1) -> 1 | G31: =+IF(SUM(B31:E31)=0,0,1) -> 1 | I31: Babecky ·et al. (2012) - Currency crisis.
A32: 31138 | B32: ='Babecky ·et al. (2012)'!B63 -> 0 | D32: =FX!F31 -> 0 | E32: 0 | F32: =+IF(SUM(B32:D32)=0,0,1) -> 0 | G32: =+IF(SUM(B32:E32)=0,0,1) -> 0
A33: 31229 | B33: ='Babecky ·et al. (2012)'!B64 -> 0 | D33: =FX!F32 -> 1 | E33: 0 | F33: =+IF(SUM(B33:D33)=0,0,1) -> 1 | G33: =+IF(SUM(B33:E33)=0,0,1) -> 1 | I33: FX (US/IE) substantial decline - Currency crisis.
A34: 31321 | B34: ='Babecky ·et al. (2012)'!B65 -> 0 | D34: =FX!F33 -> 1 | E34: 0 | F34: =+IF(SUM(B34:D34)=0,0,1) -> 1 | G34: =+IF(SUM(B34:E34)=0,0,1) -> 1
A35: 31413 | B35: ='Babecky ·et al. (2012)'!B66 -> 0 | D35: =FX!F34 -> 1 | E35: 0 | F35: =+IF(SUM(B35:D35)=0,0,1) -> 1 | G35: =+IF(SUM(B35:E35)=0,0,1) -> 1
A36: 31503 | B36: ='Babecky ·et al. (2012)'!B67 -> 0 | D36: =FX!F35 -> 1 | E36: 0 | F36: =+IF(SUM(B36:D36)=0,0,1) -> 1 | G36: =+IF(SUM(B36:E36)=0,0,1) -> 1
A37: 31594 | B37: ='Babecky ·et al. (2012)'!B68 -> 0 | D37: =FX!F36 -> 1 | E37: 0 | F37: =+IF(SUM(B37:D37)=0,0,1) -> 1 | G37: =+IF(SUM(B37:E37)=0,0,1) -> 1
A38: 31686 | B38: ='Babecky ·et al. (2012)'!B69 -> 0 | D38: =FX!F37 -> 1 | E38: 0 | F38: =+IF(SUM(B38:D38)=0,0,1) -> 1 | G38: =+IF(SUM(B38:E38)=0,0,1) -> 1
A39: 31778 | B39: ='Babecky ·et al. (2012)'!B70 -> 0 | D39: =FX!F38 -> 1 | E39: 0 | F39: =+IF(SUM(B39:D39)=0,0,1) -> 1 | G39: =+IF(SUM(B39:E39)=0,0,1) -> 1
A40: 31868 | B40: ='Babecky ·et al. (2012)'!B71 -> 0 | D40: =FX!F39 -> 1 | E40: 0 | F40: =+IF(SUM(B40:D40)=0,0,1) -> 1 | G40: =+IF(SUM(B40:E40)=0,0,1) -> 1
A41: 31959 | B41: ='Babecky ·et al. (2012)'!B72 -> 0 | D41: =FX!F40 -> 1 | E41: 0 | F41: =+IF(SUM(B41:D41)=0,0,1) -> 1 | G41: =+IF(SUM(B41:E41)=0,0,1) -> 1
A42: 32051 | B42: ='Babecky ·et al. (2012)'!B73 -> 0 | D42: =FX!F41 -> 1 | E42: 0 | F42: =+IF(SUM(B42:D42)=0,0,1) -> 1 | G42: =+IF(SUM(B42:E42)=0,0,1) -> 1
A43: 32143 | B43: ='Babecky ·et al. (2012)'!B74 -> 0 | D43: =FX!F42 -> 1 | E43: 0 | F43: =+IF(SUM(B43:D43)=0,0,1) -> 1 | G43: =+IF(SUM(B43:E43)=0,0,1) -> 1
A44: 32234 | B44: ='Babecky ·et al. (2012)'!B75 -> 0 | D44: =FX!F43 -> 1 | E44: 0 | F44: =+IF(SUM(B44:D44)=0,0,1) -> 1 | G44: =+IF(SUM(B44:E44)=0,0,1) -> 1
A45: 32325 | B45: ='Babecky ·et al. (2012)'!B76 -> 0 | D45: =FX!F44 -> 0 | E45: 0 | F45: =+IF(SUM(B45:D45)=0,0,1) -> 0 | G45: =+IF(SUM(B45:E45)=0,0,1) -> 0
... A50: 32782 | B50: ='Babecky ·et al. (2012)'!B81 -> 0 | D50: =FX!F49 -> 0 | E50: 0 | F50: =+IF(SUM(B50:D50)=0,0,1) -> 0 | G50: =+IF(SUM(B50:E50)=0,0,1) -> 0
A51: 32874 | B51: ='Babecky ·et al. (2012)'!B82 -> 0 | D51: =FX!F50 -> 0 | E51: 1 | F51: =+IF(SUM(B51:D51)=0,0,1) -> 0 | G51: =+IF(SUM(B51:E51)=0,0,1) -> 1 | I51: Baron and Dieckelmann (2022) -Bank Eq. 30% decline.
A52: 32964 | B52: ='Babecky ·et al. (2012)'!B83 -> 0 | D52: =FX!F51 -> 0 | E52: 1 | F52: =+IF(SUM(B52:D52)=0,0,1) -> 0 | G52: =+IF(SUM(B52:E52)=0,0,1) -> 1
A53: 33055 | B53: ='Babecky ·et al. (2012)'!B84 -> 0 | D53: =FX!F52 -> 0 | E53: 1 | F53: =+IF(SUM(B53:D53)=0,0,1) -> 0 | G53: =+IF(SUM(B53:E53)=0,0,1) -> 1
A54: 33147 | B54: ='Babecky ·et al. (2012)'!B85 -> 0 | D54: =FX!F53 -> 0 | E54: 1 | F54: =+IF(SUM(B54:D54)=0,0,1) -> 0 | G54: =+IF(SUM(B54:E54)=0,0,1) -> 1
A55: 33239 | B55: ='Babecky ·et al. (2012)'!B86 -> 0 | D55: =FX!F54 -> 0 | E55: 0 | F55: =+IF(SUM(B55:D55)=0,0,1) -> 0 | G55: =+IF(SUM(B55:E55)=0,0,1) -> 0
A56: 33329 | B56: ='Babecky ·et al. (2012)'!B87 -> 0 | D56: =FX!F55 -> 0 | E56: 0 | F56: =+IF(SUM(B56:D56)=0,0,1) -> 0 | G56: =+IF(SUM(B56:E56)=0,0,1) -> 0
A57: 33420 | B57: ='Babecky ·et al. (2012)'!B88 -> 0 | D57: =FX!F56 -> 0 | E57: 0 | F57: =+IF(SUM(B57:D57)=0,0,1) -> 0 | G57: =+IF(SUM(B57:E57)=0,0,1) -> 0
A58: 33512 | B58: ='Babecky ·et al. (2012)'!B89 -> 0 | D58: =FX!F57 -> 0 | E58: 0 | F58: =+IF(SUM(B58:D58)=0,0,1) -> 0 | G58: =+IF(SUM(B58:E58)=0,0,1) -> 0
A59: 33604 | B59: ='Babecky ·et al. (2012)'!B90 -> 0 | D59: =FX!F58 -> 0 | E59: 0 | F59: =+IF(SUM(B59:D59)=0,0,1) -> 0 | G59: =+IF(SUM(B59:E59)=0,0,1) -> 0
A60: 33695 | B60: ='Babecky ·et al. (2012)'!B91 -> 0 | D60: =FX!F59 -> 0 | E60: 0 | F60: =+IF(SUM(B60:D60)=0,0,1) -> 0 | G60: =+IF(SUM(B60:E60)=0,0,1) -> 0
A61: 33786 | B61: ='Babecky ·et al. (2012)'!B92 -> 0 | D61: =FX!F60 -> 0 | E61: 0 | F61: =+IF(SUM(B61:D61)=0,0,1) -> 0 | G61: =+IF(SUM(B61:E61)=0,0,1) -> 0
A62: 33878 | B62: ='Babecky ·et al. (2012)'!B93 -> 0 | D62: =FX!F61 -> 0 | E62: 0 | F62: =+IF(SUM(B62:D62)=0,0,1) -> 0 | G62: =+IF(SUM(B62:E62)=0,0,1) -> 0
A63: 33970 | B63: ='Babecky ·et al. (2012)'!B94 -> 0 | D63: =FX!F62 -> 0 | E63: 0 | F63: =+IF(SUM(B63:D63)=0,0,1) -> 0 | G63: =+IF(SUM(B63:E63)=0,0,1) -> 0
... A122: 39356 | B122: ='Babecky ·et al. (2012)'!B153 -> 0 | D122: =FX!F121 -> 0 | E122: 0 | F122: =+IF(SUM(B122:D122)=0,0,1) -> 0 | G122: =+IF(SUM(B122:E122)=0,0,1) -> 0
A123: 39448 | B123: ='Babecky ·et al. (2012)'!B154 -> 1 | C123: 1 | D123: =FX!F122 -> 0 | E123: 0 | F123: =+IF(SUM(B123:D123)=0,0,1) -> 1 | G123: =+IF(SUM(B123:E123)=0,0,1) -> 1 | I123: Laeven and Valencia (2020) - Systemic Banking Crisis - Anglo Irish Bank failed and was nationalized in 2009.
A124: 39539 | B124: ='Babecky ·et al. (2012)'!B155 -> 1 | C124: 1 | D124: =FX!F123 -> 0 | E124: 0 | F124: =+IF(SUM(B124:D124)=0,0,1) -> 1 | G124: =+IF(SUM(B124:E124)=0,0,1) -> 1
A125: 39630 | B125: ='Babecky ·et al. (2012)'!B156 -> 1 | C125: 1 | D125: =FX!F124 -> 0 | E125: 1 | F125: =+IF(SUM(B125:D125)=0,0,1) -> 1 | G125: =+IF(SUM(B125:E125)=0,0,1) -> 1
A126: 39722 | B126: ='Babecky ·et al. (2012)'!B157 -> 1 | C126: 1 | D126: =FX!F125 -> 0 | E126: 0 | F126: =+IF(SUM(B126:D126)=0,0,1) -> 1 | G126: =+IF(SUM(B126:E126)=0,0,1) -> 1
A127: 39814 | B127: ='Babecky ·et al. (2012)'!B158 -> 1 | C127: 1 | D127: =FX!F126 -> 0 | E127: 0 | F127: =+IF(SUM(B127:D127)=0,0,1) -> 1 | G127: =+IF(SUM(B127:E127)=0,0,1) -> 1
A128: 39904 | B128: ='Babecky ·et al. (2012)'!B159 -> 1 | C128: 1 | D128: =FX!F127 -> 0 | E128: 0 | F128: =+IF(SUM(B128:D128)=0,0,1) -> 1 | G128: =+IF(SUM(B128:E128)=0,0,1) -> 1
A129: 39995 | B129: ='Babecky ·et al. (2012)'!B160 -> 1 | C129: 1 | D129: =FX!F128 -> 0 | E129: 0 | F129: =+IF(SUM(B129:D129)=0,0,1) -> 1 | G129: =+IF(SUM(B129:E129)=0,0,1) -> 1
A130: 40087 | B130: ='Babecky ·et al. (2012)'!B161 -> 1 | C130: 1 | D130: =FX!F129 -> 0 | E130: 0 | F130: =+IF(SUM(B130:D130)=0,0,1) -> 1 | G130: =+IF(SUM(B130:E130)=0,0,1) -> 1
A131: 40179 | B131: ='Babecky ·et al. (2012)'!B162 -> 1 | C131: 1 | D131: =FX!F130 -> 0 | E131: 0 | F131: =+IF(SUM(B131:D131)=0,0,1) -> 1 | G131: =+IF(SUM(B131:E131)=0,0,1) -> 1
A132: 40269 | B132: ='Babecky ·et al. (2012)'!B163 -> 0 | C132: 1 | D132: =FX!F131 -> 0 | E132: 0 | F132: =+IF(SUM(B132:D132)=0,0,1) -> 1 | G132: =+IF(SUM(B132:E132)=0,0,1) -> 1
A133: 40360 | B133: ='Babecky ·et al. (2012)'!B164 -> 1 | C133: 1 | D133: =FX!F132 -> 0 | E133: 0 | F133: =+IF(SUM(B133:D133)=0,0,1) -> 1 | G133: =+IF(SUM(B133:E133)=0,0,1) -> 1 | I133: Laeven and Valencia (2020) - Systemic Banking Crisis -Bank of Ireland was bailed out and EBS Building Society was nationalized.
A134: 40452 | B134: ='Babecky ·et al. (2012)'!B165 -> 1 | C134: 1 | D134: =FX!F133 -> 0 | E134: 1 | F134: =+IF(SUM(B134:D134)=0,0,1) -> 1 | G134: =+IF(SUM(B134:E134)=0,0,1) -> 1
A135: 40544 | B135: ='Babecky ·et al. (2012)'!B166 -> 0 | C135: 1 | D135: =FX!F134 -> 0 | E135: 0 | F135: =+IF(SUM(B135:D135)=0,0,1) -> 1 | G135: =+IF(SUM(B135:E135)=0,0,1) -> 1
A136: 40634 | B136: ='Babecky ·et al. (2012)'!B167 -> 0 | C136: 1 | D136: =FX!F135 -> 0 | E136: 0 | F136: =+IF(SUM(B136:D136)=0,0,1) -> 1 | G136: =+IF(SUM(B136:E136)=0,0,1) -> 1
A137: 40725 | B137: ='Babecky ·et al. (2012)'!B168 -> 0 | C137: 1 | D137: =FX!F136 -> 0 | E137: 0 | F137: =+IF(SUM(B137:D137)=0,0,1) -> 1 | G137: =+IF(SUM(B137:E137)=0,0,1) -> 1
A138: 40817 | B138: ='Babecky ·et al. (2012)'!B169 -> 0 | C138: 1 | D138: =FX!F137 -> 0 | E138: 0 | F138: =+IF(SUM(B138:D138)=0,0,1) -> 1 | G138: =+IF(SUM(B138:E138)=0,0,1) -> 1
A139: 40909 | B139: ='Babecky ·et al. (2012)'!B170 -> 0 | C139: 1 | D139: =FX!F138 -> 0 | E139: 0 | F139: =+IF(SUM(B139:D139)=0,0,1) -> 1 | G139: =+IF(SUM(B139:E139)=0,0,1) -> 1
A140: 41000 | B140: ='Babecky ·et al. (2012)'!B171 -> 0 | C140: 1 | D140: =FX!F139 -> 0 | E140: 0 | F140: =+IF(SUM(B140:D140)=0,0,1) -> 1 | G140: =+IF(SUM(B140:E140)=0,0,1) -> 1
A141: 41091 | B141: ='Babecky ·et al. (2012)'!B172 -> 0 | C141: 1 | D141: =FX!F140 -> 0 | E141: 0 | F141: =+IF(SUM(B141:D141)=0,0,1) -> 1 | G141: =+IF(SUM(B141:E141)=0,0,1) -> 1
A142: 41183 | B142: ='Babecky ·et al. (2012)'!B173 -> 0 | C142: 1 | D142: =FX!F141 -> 0 | E142: 0 | F142: =+IF(SUM(B142:D142)=0,0,1) -> 1 | G142: =+IF(SUM(B142:E142)=0,0,1) -> 1
A143: 41275 | B143: ='Babecky ·et al. (2012)'!B174 -> 0 | D143: =FX!F142 -> 0 | E143: 0 | F143: =+IF(SUM(B143:D143)=0,0,1) -> 0 | G143: =+IF(SUM(B143:E143)=0,0,1) -> 0
A144: 41365 | B144: ='Babecky ·et al. (2012)'!B175 -> 0 | D144: =FX!F143 -> 0 | E144: 0 | F144: =+IF(SUM(B144:D144)=0,0,1) -> 0 | G144: =+IF(SUM(B144:E144)=0,0,1) -> 0
A145: 41456 | B145: ='Babecky ·et al. (2012)'!B176 -> 0 | D145: =FX!F144 -> 0 | E145: 0 | F145: =+IF(SUM(B145:D145)=0,0,1) -> 0 | G145: =+IF(SUM(B145:E145)=0,0,1) -> 0
A146: 41548 | B146: ='Babecky ·et al. (2012)'!B177 -> 0 | D146: =FX!F145 -> 0 | E146: 0 | F146: =+IF(SUM(B146:D146)=0,0,1) -> 0 | G146: =+IF(SUM(B146:E146)=0,0,1) -> 0
A147: 41640 | B147: ='Babecky ·et al. (2012)'!B178 -> 0 | D147: =FX!F146 -> 0 | E147: 0 | F147: =+IF(SUM(B147:D147)=0,0,1) -> 0 | G147: =+IF(SUM(B147:E147)=0,0,1) -> 0
A148: 41730 | B148: ='Babecky ·et al. (2012)'!B179 -> 0 | D148: =FX!F147 -> 0 | E148: 0 | F148: =+IF(SUM(B148:D148)=0,0,1) -> 0 | G148: =+IF(SUM(B148:E148)=0,0,1) -> 0
A149: 41821 | B149: ='Babecky ·et al. (2012)'!B180 -> 0 | D149: =FX!F148 -> 0 | E149: 0 | F149: =+IF(SUM(B149:D149)=0,0,1) -> 0 | G149: =+IF(SUM(B149:E149)=0,0,1) -> 0
A150: 41913 | B150: ='Babecky ·et al. (2012)'!B181 -> 0 | D150: =FX!F149 -> 0 | E150: 0 | F150: =+IF(SUM(B150:D150)=0,0,1) -> 0 | G150: =+IF(SUM(B150:E150)=0,0,1) -> 0
A151: 42005 | B151: ='Babecky ·et al. (2012)'!B182 -> 0 | D151: =FX!F150 -> 0 | E151: 0 | F151: =+IF(SUM(B151:D151)=0,0,1) -> 0 | G151: =+IF(SUM(B151:E151)=0,0,1) -> 0
A152: 42095 | B152: ='Babecky ·et al. (2012)'!B183 -> 0 | D152: =FX!F151 -> 0 | E152: 0 | F152: =+IF(SUM(B152:D152)=0,0,1) -> 0 | G152: =+IF(SUM(B152:E152)=0,0,1) -> 0
A153: 42186 | B153: ='Babecky ·et al. (2012)'!B184 -> 0 | D153: =FX!F152 -> 0 | E153: 0 | F153: =+IF(SUM(B153:D153)=0,0,1) -> 0 | G153: =+IF(SUM(B153:E153)=0,0,1) -> 0
A154: 42278 | B154: ='Babecky ·et al. (2012)'!B185 -> 0 | D154: =FX!F153 -> 0 | E154: 0 | F154: =+IF(SUM(B154:D154)=0,0,1) -> 0 | G154: =+IF(SUM(B154:E154)=0,0,1) -> 0
A155: 42370 | B155: ='Babecky ·et al. (2012)'!B186 -> 0 | D155: =FX!F154 -> 0 | E155: 1 | F155: =+IF(SUM(B155:D155)=0,0,1) -> 0 | G155: =+IF(SUM(B155:E155)=0,0,1) -> 1 | I155: Baron and Dieckelmann (2022) -Bank Eq. 30% decline.
A156: 42461 | B156: ='Babecky ·et al. (2012)'!B187 -> 0 | D156: =FX!F155 -> 0 | E156: 1 | F156: =+IF(SUM(B156:D156)=0,0,1) -> 0 | G156: =+IF(SUM(B156:E156)=0,0,1) -> 1
A157: 42552 | B157: ='Babecky ·et al. (2012)'!B188 -> 0 | D157: =FX!F156 -> 0 | E157: 1 | F157: =+IF(SUM(B157:D157)=0,0,1) -> 0 | G157: =+IF(SUM(B157:E157)=0,0,1) -> 1
A158: 42644 | B158: ='Babecky ·et al. (2012)'!B189 -> 0 | D158: =FX!F157 -> 0 | E158: 1 | F158: =+IF(SUM(B158:D158)=0,0,1) -> 0 | G158: =+IF(SUM(B158:E158)=0,0,1) -> 1
A159: 42736 | B159: ='Babecky ·et al. (2012)'!B190 -> 0 | D159: =FX!F158 -> 0 | E159: 0 | F159: =+IF(SUM(B159:D159)=0,0,1) -> 0 | G159: =+IF(SUM(B159:E159)=0,0,1) -> 0
A160: 42826 | B160: ='Babecky ·et al. (2012)'!B191 -> 0 | D160: =FX!F159 -> 0 | E160: 0 | F160: =+IF(SUM(B160:D160)=0,0,1) -> 0 | G160: =+IF(SUM(B160:E160)=0,0,1) -> 0
A161: 42917 | B161: ='Babecky ·et al. (2012)'!B192 -> 0 | D161: =FX!F160 -> 0 | E161: 0 | F161: =+IF(SUM(B161:D161)=0,0,1) -> 0 | G161: =+IF(SUM(B161:E161)=0,0,1) -> 0
A162: 43009 | B162: ='Babecky ·et al. (2012)'!B193 -> 0 | D162: =FX!F161 -> 0 | E162: 0 | F162: =+IF(SUM(B162:D162)=0,0,1) -> 0 | G162: =+IF(SUM(B162:E162)=0,0,1) -> 0
A163: 43101 | B163: ='Babecky ·et al. (2012)'!B194 -> 0 | D163: =FX!F162 -> 0 | E163: 0 | F163: =+IF(SUM(B163:D163)=0,0,1) -> 0 | G163: =+IF(SUM(B163:E163)=0,0,1) -> 0
A164: 43191 | B164: ='Babecky ·et al. (2012)'!B195 -> 0 | D164: =FX!F163 -> 0 | E164: 0 | F164: =+IF(SUM(B164:D164)=0,0,1) -> 0 | G164: =+IF(SUM(B164:E164)=0,0,1) -> 0
A165: 43282 | B165: ='Babecky ·et al. (2012)'!B196 -> 0 | D165: =FX!F164 -> 0 | E165: 0 | F165: =+IF(SUM(B165:D165)=0,0,1) -> 0 | G165: =+IF(SUM(B165:E165)=0,0,1) -> 0
A166: 43374 | B166: ='Babecky ·et al. (2012)'!B197 -> 0 | D166: =FX!F165 -> 0 | E166: 0 | F166: =+IF(SUM(B166:D166)=0,0,1) -> 0 | G166: =+IF(SUM(B166:E166)=0,0,1) -> 0
A167: 43466 | B167: ='Babecky ·et al. (2012)'!B198 -> 0 | D167: =FX!F166 -> 0 | E167: 0 | F167: =+IF(SUM(B167:D167)=0,0,1) -> 0 | G167: =+IF(SUM(B167:E167)=0,0,1) -> 0
... A192: 45748 | B192: ='Babecky ·et al. (2012)'!B223 -> 0 | D192: =FX!F191 -> 0 | E192: 0 | F192: =+IF(SUM(B192:D192)=0,0,1) -> 0 | G192: =+IF(SUM(B192:E192)=0,0,1) -> 0

Sheet FX
A1: Date | B1: FX | C1: hp_trend_FX | D1: hp_cycle_FX | E1: FX_yoy | F1: Dummy_currency_crisis | G1: Babecky ·et al. (2012
A2: 28491 | B2: 0.65827454 | C2: 0.57077996 | D2: 0.087494587
A3: 28581 | B3: 0.69183795 | C3: 0.58566262 | D3: 0.10617533
A4: 28672 | B4: 0.6578513 | C4: 0.60059997 | D4: 0.057251333
A5: 28764 | B5: 0.64024426 | C5: 0.61571304 | D5: 0.024531225
A6: 28856 | B6: 0.63004403 | C6: 0.63115867 | D6: -0.0011146312 | E6: =B6/B2-1 -> -0.042885617
A7: 28946 | B7: 0.63419185 | C7: 0.647109 | D7: -0.012917159 | E7: =B7/B3-1 -> -0.083323137
A8: 29037 | B8: 0.61256397 | C8: 0.66373552 | D8: -0.051171542 | E8: =B8/B4-1 -> -0.068841279
A9: 29129 | B9: 0.6048609 | C9: 0.68120159 | D9: -0.076340691 | E9: =B9/B5-1 -> -0.055265419
A10: 29221 | B10: 0.60837384 | C10: 0.69963862 | D10: -0.091264787 | E10: =B10/B6-1 -> -0.034394733
A11: 29312 | B11: 0.61641551 | C11: 0.71913032 | D11: -0.10271481 | E11: =B11/B7-1 -> -0.028029899
A12: 29403 | B12: 0.59838523 | C12: 0.73970333 | D12: -0.1413181 | E12: =B12/B8-1 -> -0.023146549
A13: 29495 | B13: 0.64862454 | C13: 0.7613201 | D13: -0.11269557 | E13: =B13/B9-1 -> 0.072353229
A14: 29587 | B14: 0.71676715 | C14: 0.78385478 | D14: -0.067087632 | E14: =B14/B10-1 -> 0.17816892
A15: 29677 | B15: 0.79062358 | C15: 0.80711105 | D15: -0.01648747 | E15: =B15/B11-1 -> 0.28261467
A16: 29768 | B16: 0.84687297 | C16: 0.83085068 | D16: 0.016022295 | E16: =B16/B12-1 -> 0.41526383
A17: 29860 | B17: 0.80310933 | C17: 0.85482514 | D17: -0.051715801 | E17: =B17/B13-1 -> 0.23817292
... A29: 30956 | B29: 1.2480679 | C29: 1.0564764 | D29: 0.19159149 | E29: =B29/B25-1 -> 0.13963285
A30: 31048 | B30: 1.3266647 | C30: 1.0574893 | D30: 0.26917536 | E30: =B30/B26-1 -> 0.191191 | G30: 1 | H30: Babecky ·et al. (2012), starting point of the currency crisis. We extend the period for what the FX fall after this quarter
A31: 31138 | B31: 1.2520887 | C31: 1.05538 | D31: 0.19670875 | E31: =B31/B27-1 -> 0.11562394
A32: 31229 | B32: 1.1616834 | C32: 1.0503725 | D32: 0.11131084 | E32: =B32/B28-1 -> -0.034168485 | F32: 1
A33: 31321 | B33: 1.0628977 | C33: 1.0428141 | D33: 0.020083601 | E33: =B33/B29-1 -> -0.14836544 | F33: 1
A34: 31413 | B34: 0.98404701 | C34: 1.0331215 | D34: -0.049074485 | E34: =B34/B30-1 -> -0.25825491 | F34: 1
A35: 31503 | B35: 0.93867504 | C35: 1.0217238 | D35: -0.0830488 | E35: =B35/B31-1 -> -0.25031268 | F35: 1
A36: 31594 | B36: 0.93435793 | C36: 1.0090197 | D36: -0.074661818 | E36: =B36/B32-1 -> -0.19568623 | F36: 1
A37: 31686 | B37: 0.93490815 | C37: 0.99535589 | D37: -0.060447746 | E37: =B37/B33-1 -> -0.12041572 | F37: 1
A38: 31778 | B38: 0.87362212 | C38: 0.98103229 | D38: -0.10741017 | E38: =B38/B34-1 -> -0.11221505 | F38: 1
A39: 31868 | B39: 0.85664996 | C39: 0.96631116 | D39: -0.10966121 | E39: =B39/B35-1 -> -0.087383894 | F39: 1
A40: 31959 | B40: 0.87027848 | C40: 0.95138761 | D40: -0.081109133 | E40: =B40/B36-1 -> -0.068581265 | F40: 1
A41: 32051 | B41: 0.81500255 | C41: 0.93638819 | D41: -0.12138565 | E41: =B41/B37-1 -> -0.12825388 | F41: 1
A42: 32143 | B42: 0.80035824 | C42: 0.89710243 | D42: -0.096744192 | E42: =B42/B38-1 -> -0.083862216 | F42: 1
A43: 32234 | B43: 0.81017754 | C43: 0.86550676 | D43: -0.055329215 | E43: =B43/B39-1 -> -0.054249012 | F43: 1
A44: 32325 | B44: 0.88301818 | C44: 0.85362823 | D44: 0.029389958 | E44: =B44/B40-1 -> 0.014638654
A45: 32417 | B45: 0.84285214 | C45: 0.83673136 | D45: 0.0061207781 | E45: =B45/B41-1 -> 0.034171167
A46: 32509 | B46: 0.87967454 | C46: 0.83074809 | D46: 0.048926448 | E46: =B46/B42-1 -> 0.099101005
A47: 32599 | B47: 0.91912107 | C47: 0.83497152 | D47: 0.084149547 | E47: =B47/B43-1 -> 0.13446871
A48: 32690 | B48: 0.91548115 | C48: 0.83949807 | D48: 0.075983084 | E48: =B48/B44-1 -> 0.036763649
A49: 32782 | B49: 0.86972826 | C49: 0.83563728 | D49: 0.034090975 | E49: =B49/B45-1 -> 0.031887115
A50: 32874 | B50: 0.80903478 | C50: 0.82113894 | D50: -0.012104156 | E50: =B50/B46-1 -> -0.080302156
A51: 32964 | B51: 0.79506766 | C51: 0.80647664 | D51: -0.011408975 | E51: =B51/B47-1 -> -0.13496961
A52: 33055 | B52: 0.75375885 | C52: 0.78621492 | D52: -0.032456071 | E52: =B52/B48-1 -> -0.1766528
A53: 33147 | B53: 0.7132542 | C53: 0.76116781 | D53: -0.047913611 | E53: =B53/B49-1 -> -0.17991143
A54: 33239 | B54: 0.73005707 | C54: 0.74344336 | D54: -0.013386285 | E54: =B54/B50-1 -> -0.09761967
A55: 33329 | B55: 0.82579532 | C55: 0.74817581 | D55: 0.077619511 | E55: =B55/B51-1 -> 0.038647857
... A98: 37257 | B98: 1.140733 | C98: 1.1529669 | D98: -0.012233918 | E98: =B98/B94-1 -> 0.052496808

Sheet Babecky ·et al. (2012)
A1: TYPE OF EVENT | B1: BANKING CRISES | C1: CURRENCY (BOP) CRISES | D1: DEBT CRISES | E1: all
A2: 1970 - I. | B2: 0 | C2: 0 | D2: 0 | E2: =IF(SUM(B2:D2)=0,0,1) -> 0
A3: 1970 - II. | B3: 0 | C3: 0 | D3: 0 | E3: =IF(SUM(B3:D3)=0,0,1) -> 0
A4: 1970 - III. | B4: 0 | C4: 0 | D4: 0 | E4: =IF(SUM(B4:D4)=0,0,1) -> 0
A5: 1970 - IV. | B5: 0 | C5: 0 | D5: 0 | E5: =IF(SUM(B5:D5)=0,0,1) -> 0
A6: 1971 - I. | B6: 0 | C6: 0 | D6: 0 | E6: =IF(SUM(B6:D6)=0,0,1) -> 0
A7: 1971 - II. | B7: 0 | C7: 0 | D7: 0 | E7: =IF(SUM(B7:D7)=0,0,1) -> 0
A8: 1971 - III. | B8: 0 | C8: 0 | D8: 0 | E8: =IF(SUM(B8:D8)=0,0,1) -> 0
A9: 1971 - IV. | B9: 0 | C9: 0 | D9: 0 | E9: =IF(SUM(B9:D9)=0,0,1) -> 0
A10: 1972 - I. | B10: 0 | C10: 0 | D10: 0 | E10: =IF(SUM(B10:D10)=0,0,1) -> 0
A11: 1972 - II. | B11: 0 | C11: 0 | D11: 0 | E11: =IF(SUM(B11:D11)=0,0,1) -> 0
A12: 1972 - III. | B12: 0 | C12: 0 | D12: 0 | E12: =IF(SUM(B12:D12)=0,0,1) -> 0
A13: 1972 - IV. | B13: 0 | C13: 0 | D13: 0 | E13: =IF(SUM(B13:D13)=0,0,1) -> 0
... A165: 2010 - IV. | B165: 1 | C165: 0 | D165: 1 | E165: =IF(SUM(B165:D165)=0,0,1) -> 1

Sheet Laeven and Valencia (2020)
A1: Country | B1: Start | C1: End | D1: Output loss 1/ | E1: Fiscal Costs 2/ (% of GDP) | F1: Fiscal Costs, net 2/ (% of GDP) | G1: Fiscal cost (% of financial sector assets) | H1: Peak liquidity 3/ | I1: Liquidity support 3/ | J1: Peak NPLs 4/ | K1: Increase in public debt 5/
A2: Albania | B2: 1994 | C2: 1994 | D2: … | E2: ... | F2: ... | G2: ... | H2: 7.615962 | I2: ... | J2: 26.8 | K2: ...
A3: Algeria | B3: 1990 | C3: 1994 7/ | D3: 41.392253 | E3: ... | F3: ... | G3: ... | H3: 37.56032 | I3: 29.85246 | J3: 30 | K3: 19.10056
A4: Argentina | B4: 1980 | C4: 1982 6/ | D4: 58.171235 | E4: 55.1 | F4: 55.1 | G4: 213.89751 | H4: 64.64586 | I4: 62.21225 | J4: 9 | K4: 33.14739
A5: Argentina | B5: 1989 | C5: 1991 | D5: 12.629947 | E5: 6 | F5: 6 | G5: 21.606049 | H5: 151.5721 | I5: 135.665 | J5: 27 | K5: -21.29261
A6: Argentina 8/ | B6: 1995 | C6: 1995 | D6: 0 | E6: 2 | F6: 2 | G6: 8.550663 | H6: 71.3528 | I6: 62.99766 | J6: 17 | K6: 8.69467
A7: Argentina | B7: 2001 | C7: 2003 | D7: 70.974199 | E7: 9.6 | F7: 9.5846645 | G7: 28.094822 | H7: 22.85839 | I7: 22.64661 | J7: 20.1 | K7: 81.88721
A8: Armenia 4/ | B8: 1994 | C8: 1994 6/ | D8: … | E8: ... | F8: ... | G8: ... | H8: 41.37691 | I8: 22.99402 | J8: ... | K8: ...
A9: Austria | B9: 2008 | C9: 2012 7/ | D9: 19.215918 | E9: =+'[1]Additional Details-Bk Crises'!F47*100 -> 5.15 | F9: 1.64 | G9: 1.6435314 | H9: 10.02 | I9: 6.41 | J9: =+'[1]Additional Details-Bk Crises'!F45*100 -> 4.1 | K9: 19.8
A10: Azerbaijan | B10: 1995 | C10: 1995 6/ | D10: ... | E10: ... | F10: ... | G10: ... | H10: 127.5802 | I10: 84.46377 | J10: ... | K10: 0.89603
A11: Bangladesh | B11: 1987 | C11: 1987 | D11: 0 | E11: ... | F11: ... | G11: ... | H11: 25.96208 | I11: 2.82342 | J11: 20 | K11: 3.4759
A12: Belarus | B12: 1995 | C12: 1995 | D12: ... | E12: ... | F12: ... | G12: ... | H12: 35.7598 | I12: ... | J12: ... | K12: -16.45655
A13: Belgium | B13: 2008 | C13: 2012 7/ | D13: 15.732718 | E13: =+'[1]Additional Details-Bk Crises'!G47*100 -> 6.15 | F13: 0.46 | G13: 1.6283828 | H13: 13.69 | I13: 9.67 | J13: =100*'[1]Additional Details-Bk Crises'!G45 -> 4.24 | K13: 22.2
A14: Benin | B14: 1988 | C14: 1992 7/ | D14: 14.917588 | E14: 17 | F14: ... | G14: 64.320847 | H14: 99.64091 | I14: 48.62441 | J14: 80 | K14: 5.67801
A15: Bolivia | B15: 1986 | C15: 1986 | D15: 49.191735 | E15: ... | F15: ... | G15: ... | H15: 57.52545 | I15: 25.92482 | J15: 30 | K15: -107.2825
A16: Bolivia | B16: 1994 | C16: 1994 | D16: 0 | E16: 6 | F16: 2.6533333 | G16: 15.193719 | H16: 31.92642 | I16: 12.89265 | J16: 6.2 | K16: -19.21072
A17: Bosnia and Herzegovina | B17: 1992 | C17: 1996 7/ | D17: ... | E17: ... | F17: ... | G17: ... | H17: ... | I17: ... | J17: ... | K17: ...
A18: Brazil 8/ | B18: 1990 | C18: 1994 7/ | D18: 62.295604 | E18: 0 | F18: 0 | G18: 0 | H18: 11.26261 | I18: 10.71347 | J18: ... | K18: -22.64
A19: Brazil | B19: 1994 | C19: 1998 | D19: 0 | E19: 13.2 | F19: 10.2 | G19: 28.596188 | H19: 20.11846 | I19: 17.61162 | J19: 16 | K19: -33.77793
A20: Bulgaria | B20: 1996 | C20: 1997 | D20: 59.510493 | E20: 14 | F20: 13.9 | G20: 21.370783 | H20: 17.30571 | I20: 9.93675 | J20: 75 | K20: -30.07973
A21: Burkina Faso | B21: 1990 | C21: 1994 | D21: ... | E21: ... | F21: ... | G21: ... | H21: 9.3824 | I21: 4.51769 | J21: 16 | K21: 8.92432
A22: Burundi | B22: 1994 | C22: 1998 7/ | D22: 121.192 | E22: ... | F22: ... | G22: ... | H22: 23.44168 | I22: 18.25261 | J22: 25 | K22: 10.85286
A23: Cameroon | B23: 1987 | C23: 1991 7/ | D23: 105.52664 | E23: ... | F23: ... | G23: ... | H23: 59.10603 | I23: 40.85175 | J23: 65 | K23: 17.96692
A24: Cameroon | B24: 1995 | C24: 1997 | D24: 8.0982519 | E24: ... | F24: ... | G24: ... | H24: 12.31134 | I24: 6.16095 | J24: 30 | K24: -1.06627
A25: Cape Verde | B25: 1993 | C25: 1993 | D25: 0 | E25: ... | F25: ... | G25: ... | H25: 3.967447 | I25: ... | J25: 30 | K25: 18.15971
A26: Central African Rep | B26: 1976 | C26: 1976 | D26: 0 | E26: ... | F26: ... | G26: ... | H26: 90.84164 | I26: 10.4593 | J26: ... | K26: -4.77751
A27: Central African Rep | B27: 1995 | C27: 1996 | D27: 8.9569594 | E27: ... | F27: ... | G27: ... | H27: 24.83221 | I27: 20.94306 | J27: 40 | K27: -16.26852
A28: Chad | B28: 1983 | C28: 1983 | D28: 0 | E28: ... | F28: ... | G28: ... | H28: 199.305 | I28: 41.31468 | J28: ... | K28: -7.16883
A29: Chad | B29: 1992 | C29: 1996 7/ | D29: 0 | E29: ... | F29: ... | G29: ... | H29: 120.8667 | I29: 41.38313 | J29: 35 | K29: 27.0806
A30: Chile | B30: 1976 | C30: 1976 | D30: 19.89855 | E30: ... | F30: ... | G30: ... | H30: 32.20038 | I30: 23.63696 | J30: ... | K30: -69.52382
A31: Chile | B31: 1981 | C31: 1985 7/ | D31: 8.6097452 | E31: 42.9 | F31: 16.8 | G31: 134.31433 | H31: 61.22512 | I31: 52.6979 | J31: 35.6 | K31: 87.8976
A32: China, Mainland | B32: 1998 | C32: 1998 | D32: 19.398311 | E32: 18 | F32: ... | G32: 19.53125 | H32: 62.01519 | I32: 7.19216 | J32: 20 | K32: 11.15775
A33: Colombia | B33: 1982 | C33: 1982 | D33: 46.959534 | E33: 5 | F33: 5 | G33: 16.496206 | H33: 21.06028 | I33: 7.73772 | J33: 4.1 | K33: 16.57043
A34: Colombia | B34: 1998 | C34: 2000 | D34: 43.398161 | E34: 6.3 | F34: 2.54 | G34: 15.897047 | H34: 5.073536 | I34: 4.29109 | J34: 14 | K34: 15.40799
A35: Congo, Dem Rep | B35: 1983 | C35: 1983 | D35: 1.3754204 | E35: ... | F35: ... | G35: ... | H35: 19.95647 | I35: 18.91813 | J35: ... | K35: 39.45382
A36: Congo, Dem Rep | B36: 1991 | C36: 1994 7/ | D36: 129.54675 | E36: ... | F36: ... | G36: ... | H36: 44.69853 | I36: 30.17046 | J36: ... | K36: 42.1884
A37: Congo, Dem Rep | B37: 1994 | C37: 1998 7/ | D37: 78.991939 | E37: ... | F37: ... | G37: ... | H37: 77.25292 | I37: 77.11886 | J37: 75 | K37: 39.25775
A38: Congo, Rep | B38: 1992 | C38: 1994 | D38: 47.359838 | E38: ... | F38: ... | G38: ... | H38: 30.73201 | I38: 16.58411 | J38: ... | K38: 103.4631
A39: Costa Rica | B39: 1987 | C39: 1991 | D39: 0 | E39: ... | F39: ... | G39: ... | H39: 20.17417 | I39: 6.09581 | J39: ... | K39: -27.54878
A40: Costa Rica | B40: 1994 | C40: 1995 | D40: 0 | E40: ... | F40: ... | G40: ... | H40: 15.1952 | I40: 6.34947 | J40: 32 | K40: 4.75884
A41: Cote d'Ivoire | B41: 1988 | C41: 1992 7/ | D41: 45 | E41: 25 | F41: 25 | G41: 63.597046 | H41: 76.85339 | I41: 22.53789 | J41: 50 | K41: 13.61769
A42: Croatia | B42: 1998 | C42: 1999 | D42: ... | E42: 6.9 | F42: 6.9 | G42: 14.951245 | H42: 3.249792 | I42: 3.12535 | J42: 10.5 | K42: 14.0892
A43: Czech Republic 8/ | B43: 1996 | C43: 2000 7/ | D43: ... | E43: 6.8 | F43: 5.8 | G43: 9.5774651 | H43: 12.65652 | I43: 4.15161 | J43: 18 | K43: 1.77465
A44: Cyprus | B44: 2011 | C44: 2015 7/ | D44: 76.495338 | E44: =+'[1]Additional Details-Bk Crises'!R46*100 -> 17.99 | F44: 17.99 | G44: 2.5725229 | H44: 20.29 | I44: 14.06559 | J44: =+'[1]Additional Details-Bk Crises'!R45*100 -> 47.75 | K44: 21.256669
A45: Denmark | B45: 2008 | C45: 2009 | D45: 35.016396 | E45: =+'[1]Additional Details-Bk Crises'!S47*100 -> 5.94 | F45: 2.44 | G45: 3.060909 | H45: 17.7 | I45: 9.7 | J45: =+'[1]Additional Details-Bk Crises'!S45*100 -> 5.95 | K45: 32.764464
A46: Djibouti | B46: 1991 | C46: 1995 7/ | D46: 42.645263 | E46: ... | F46: ... | G46: ... | H46: 5.228449 | I46: 3.15111 | J46: ... | K46: ...
A47: Dominican Rep | B47: 2003 | C47: 2004 | D47: 12.493992 | E47: 22 | F47: 20.8 | G47: 63.712715 | H47: 43.37155 | I47: 38.11788 | J47: 9 | K47: 16.51355
A48: Ecuador | B48: 1982 | C48: 1986 7/ | D48: 98.190623 | E48: ... | F48: ... | G48: ... | H48: 146.7178 | I48: 100.011 | J48: ... | K48: 24.40191
A49: Ecuador | B49: 1998 | C49: 2002 | D49: 25.35333 | E49: 21.7 | F49: 16.26 | G49: 76.841362 | H49: 26.0049 | I49: 22.54439 | J49: 40 | K49: 9.0542
A50: Egypt | B50: 1980 | C50: 1980 | D50: 0.8829518 | E50: ... | F50: ... | G50: ... | H50: 66.65489 | I50: 22.73382 | J50: ... | K50: -4.22944
A51: El Salvador | B51: 1989 | C51: 1990 | D51: 0 | E51: ... | F51: ... | G51: ... | H51: 51.63841 | I51: 11.46209 | J51: 37 | K51: -29.55433
A52: Equatorial Guinea | B52: 1983 | C52: 1983 6/ | D52: 0 | E52: ... | F52: ... | G52: ... | H52: 75.79138 | I52: ... | J52: ... | K52: ...
A53: Eritrea | B53: 1993 | C53: 1993 6/ | D53: ... | E53: ... | F53: ... | G53: ... | H53: ... | I53: ... | J53: ... | K53: ...
A54: Estonia | B54: 1992 | C54: 1994 | D54: ... | E54: 1.9 | F54: 1.63 | G54: ... | H54: 30.92378 | I54: ... | J54: 7 | K54: ...
A55: Finland | B55: 1991 | C55: 1995 | D55: 69.590314 | E55: 12.8 | F55: 11.08 | G55: 15.492617 | H55: 11.99135 | I55: 5.50326 | J55: 13 | K55: 43.55003
A56: France 8/ | B56: 2008 | C56: 2009 | D56: 23.349285 | E56: =+'[1]Additional Details-Bk Crises'!X47*100 -> 1.26 | F56: 1.06 | G56: 0.34429803 | H56: 9.59 | I56: 8.18 | J56: =100*'[1]Additional Details-Bk Crises'!X45 -> 4.5 | K56: 15.87567
A57: Georgia | B57: 1991 | C57: 1995 7/ | D57: ... | E57: ... | F57: ... | G57: ... | H57: ... | I57: ... | J57: 33 | K57: ...
A58: Germany | B58: 2008 | C58: 2009 | D58: 12.257433 | E58: =+'[1]Additional Details-Bk Crises'!Y47*100 -> 2.73 | F58: 0.69 | G58: 0.9036836 | H58: 12.94 | I58: 4 | J58: =100*'[1]Additional Details-Bk Crises'!Y45 -> 3.7 | K58: 16.228234
A59: Ghana | B59: 1982 | C59: 1983 | D59: 45.309134 | E59: 6 | F59: 6 | G59: 105.82011 | H59: 0.1895669 | I59: 0.05728 | J59: 35 | K59: 15.5217
A60: Greece | B60: 2008 | C60: 2012 7/ | D60: 64.926102 | E60: =+'[1]Additional Details-Bk Crises'!AA47*100 -> 28.7 | F60: 17.11 | G60: 17.058182 | H60: 61.74 | I60: 59.84 | J60: =100*'[1]Additional Details-Bk Crises'!AA45 -> 37.1 | K60: 43.8704
A61: Guinea | B61: 1985 | C61: 1985 6/ | D61: 0 | E61: 3 | F61: ... | G61: ... | H61: ... | I61: ... | J61: ... | K61: ...
A62: Guinea | B62: 1993 | C62: 1993 | D62: 0 | E62: ... | F62: ... | G62: ... | H62: 14.56486 | I62: 3.93189 | J62: 45 | K62: 6.72173
A63: Guinea-Bissau | B63: 1995 | C63: 1998 | D63: 29.631113 | E63: ... | F63: ... | G63: ... | H63: 137.2966 | I63: 39.24507 | J63: 45 | K63: 108.0536
A64: Guinea-Bissau | B64: 2014 | C64: ongoing | D64: 0 | E64: ... | F64: ... | G64: ... | H64: 33.39 | I64: 22.38 | J64: 25.7 | K64: 3.1638627
A65: Guyana | B65: 1993 | C65: 1993 | D65: 0 | E65: ... | F65: ... | G65: ... | H65: 1.833009 | I65: 1.68026 | J65: ... | K65: -240.9886
A66: Haiti | B66: 1994 | C66: 1998 | D66: 37.549129 | E66: ... | F66: ... | G66: ... | H66: 4.766555 | I66: ... | J66: ... | K66: -119.382
A67: Hungary | B67: 1991 | C67: 1995 7/ | D67: 0 | E67: 10 | F67: ... | G67: 21.276596 | H67: 47.02957 | I67: 4.6216 | J67: 23 | K67: 19.6031
A68: Hungary 8/ | B68: 2008 | C68: 2012 7/ | D68: 37.309933 | E68: =+'[1]Additional Details-Bk Crises'!AB47*100 -> 2.85 | F68: 0.08 | G68: 4.0662007 | H68: 2.34 | I68: 2.2 | J68: =+'[1]Additional Details-Bk Crises'!AB45*100 -> 17.32 | K68: 3.7774047
A69: Iceland | B69: 2008 | C69: 2012 7/ | D69: 34.497215 | E69: 37.6 | F69: 3.3 | G69: 14.3 | H69: 33.82 | I69: 28.07 | J69: 61.2 | K69: 67.916974
A70: India | B70: 1993 | C70: 1993 | D70: 0 | E70: ... | F70: ... | G70: ... | H70: 4.280926 | I70: 3.62577 | J70: 20 | K70: -7.73688
A71: Indonesia | B71: 1997 | C71: 2001 7/ | D71: 69.019502 | E71: 56.8 | F71: 52.2 | G71: 105.41945 | H71: 23.12321 | I71: 17.19079 | J71: 32.5 | K71: 67.56022
A72: Ireland | B72: 2008 | C72: 2012 7/ | D72: 107.71813 | E72: =+'[1]Additional Details-Bk Crises'!AE47*100 -> 37.63 | F72: 26.76 | G72: 4.4633384 | H72: 18.05 | I72: 15.39 | J72: =100*'[1]Additional Details-Bk Crises'!AE45 -> 25.71 | K72: 76.537362
A73: Israel | B73: 1983 | C73: 1986 | D73: 42.68 | E73: 30 | F73: ... | G73: 30.86 | H73: 5.34 | I73: … | J73: ... | K73: ...
A74: Italy | B74: 2008 | C74: 2009 | D74: 32.216835 | E74: =+'[1]Additional Details-Bk Crises'!AF47*100 -> 0.73 | F74: 0.65 | G74: 0.34482989 | H74: 19.35 | I74: 17.82 | J74: =100*'[1]Additional Details-Bk Crises'!AF45 -> 18.03 | K74: 8.5882381
A75: Jamaica | B75: 1996 | C75: 1998 | D75: 37.789189 | E75: 43.9 | F75: 38.95 | G75: 161.39705 | H75: 0.370034 | I75: 0.33939 | J75: 28.9 | K75: 2.9386
A76: Japan | B76: 1997 | C76: 2001 7/ | D76: 44.99978 | E76: 8.6 | F76: 8.51 | G76: 3.1563108 | H76: 2.418041 | I76: 1.57701 | J76: 35 | K76: 41.73192
A77: Jordan | B77: 1989 | C77: 1991 | D77: 106.3742 | E77: 10 | F77: ... | G77: 12.514078 | H77: 20.66872 | I77: 16.11607 | J77: ... | K77: -61.01241
A78: Kazakhstan 8/ | B78: 2008 | C78: 2008 | D78: 0 | E78: 3.7 | F78: 3.7 | G78: 7.5356417 | H78: 6.56 | I78: 5.27 | J78: =+'[1]Additional Details-Bk Crises'!AI45*100 -> 37.7 | K78: 6.5337453
A79: Kenya | B79: 1985 | C79: 1985 | D79: 23.685191 | E79: ... | F79: ... | G79: ... | H79: 1.988765 | I79: 1.88066 | J79: ... | K79: 11.03001
A80: Kenya | B80: 1992 | C80: 1994 | D80: 50.291202 | E80: ... | F80: ... | G80: ... | H80: 25.15109 | I80: 24.26497 | J80: ... | K80: 12.05009
A81: Korea | B81: 1997 | C81: 1998 | D81: 57.58705 | E81: 31.2 | F81: 23.2 | G81: 57.216213 | H81: 27.44887 | I81: 11.92423 | J81: 35 | K81: 9.91172
A82: Kuwait | B82: 1982 | C82: 1985 | D82: 143.43406 | E82: ... | F82: ... | G82: ... | H82: 9.597325 | I82: 2.88404 | J82: 40 | K82: 16.249
A83: Kyrgyz Rep | B83: 1995 | C83: 1999 7/ | D83: ... | E83: ... | F83: ... | G83: ... | H83: 286.1311 | I83: 51.82416 | J83: 85 | K83: 42.8739
A84: Latvia | B84: 1995 | C84: 1996 | D84: ... | E84: 3 | F84: 3 | G84: 10.053619 | H84: 9.164797 | I84: 5.52545 | J84: 20 | K84: 0.42293
A85: Latvia | B85: 2008 | C85: 2012 7/ | D85: 93.924309 | E85: =+'[1]Additional Details-Bk Crises'!AL47*100 -> 8.1 | F85: 3.93 | G85: 10.959274 | H85: 3.5770264 | I85: 3.3837644 | J85: =+'[1]Additional Details-Bk Crises'!AL45*100 -> 15.93 | K85: 27.638768
A86: Lebanon | B86: 1990 | C86: 1993 | D86: 102.21529 | E86: ... | F86: ... | G86: ... | H86: 4.411205 | I86: 2.80343 | J86: ... | K86: ...
A87: Liberia | B87: 1991 | C87: 1995 7/ | D87: ... | E87: ... | F87: ... | G87: ... | H87: 85.19892 | I87: 84.22068 | J87: ... | K87: ...
A88: Lithuania | B88: 1995 | C88: 1996 | D88: ... | E88: 3.1 | F88: 2.897105 | G88: 18.787878 | H88: 27.46764 | I88: 18.87309 | J88: 32.2 | K88: 10.83184
A89: Luxembourg | B89: 2008 | C89: 2012 7/ | D89: 43.299248 | E89: =+'[1]Additional Details-Bk Crises'!AN47*100 -> 7.2 | F89: 5 | G89: 0.22642757 | H89: 5.96 | I89: 1.13 | J89: =+'[1]Additional Details-Bk Crises'!AN45*100 -> 1.67 | K89: 12.671541
A90: Macedonia, FYR | B90: 1993 | C90: 1995 | D90: 0 | E90: 32 | F90: ... | G90: ... | H90: 22.27403 | I90: ... | J90: 70 | K90: ...
A91: Madagascar | B91: 1988 | C91: 1988 | D91: 0 | E91: ... | F91: ... | G91: ... | H91: 20.17953 | I91: 19.4023 | J91: 25 | K91: -25.78864
A92: Malaysia | B92: 1997 | C92: 1999 | D92: 31.448596 | E92: 16.4 | F92: 5.1 | G92: 12.650416 | H92: 9.717911 | I92: 8.77468 | J92: 30 | K92: 0.15113
A93: Mali | B93: 1987 | C93: 1991 7/ | D93: 0 | E93: ... | F93: ... | G93: ... | H93: 50.52423 | I93: 14.83972 | J93: 75 | K93: -11.29271
A94: Mauritania | B94: 1984 | C94: 1984 | D94: 7.5051325 | E94: 15 | F94: ... | G94: 53.191486 | H94: 48.394 | I94: 27.72171 | J94: 70 | K94: ...
A95: Mexico | B95: 1981 | C95: 1985 7/ | D95: 26.581203 | E95: ... | F95: ... | G95: ... | H95: 5.303944 | I95: 2.64167 | J95: ... | K95: 22.5642
A96: Mexico | B96: 1994 | C96: 1996 | D96: 13.655375 | E96: 19.3 | F96: 18 | G96: 54.938797 | H96: 16.75267 | I96: 15.79219 | J96: 18.9 | K96: 16.3687
A97: Moldova | B97: 2014 | C97: ongoing | E97: =+'[1]Additional Details-Bk Crises'!AQ47*100 -> 11.7 | F97: 11.7 | G97: 26.139412 | H97: 24.7 | I97: 23.99 | J97: =+'[1]Additional Details-Bk Crises'!AQ45*100 -> 16.41 | K97: 19.52119
A98: Mongolia | B98: 2008 | C98: 2009 | D98: 0 | E98: =+'[1]Additional Details-Bk Crises'!AR47*100 -> 5.1 | F98: 5.1 | G98: 15.269461 | H98: 34.45 | I98: 33.22 | J98: =+'[1]Additional Details-Bk Crises'!AR45*100 -> 20 | K98: -5.0278099
A99: Morocco | B99: 1980 | C99: 1984 7/ | D99: 21.924525 | E99: ... | F99: ... | G99: ... | H99: 22.08919 | I99: 8.63237 | J99: ... | K99: 35.6461
A100: Mozambique | B100: 1987 | C100: 1991 7/ | D100: 0 | E100: ... | F100: ... | G100: ... | H100: 4.198764 | I100: 4.17345 | J100: ... | K100: 60.8565
...

Sheet Baron and Dieckelmann (2022)
A1: Country | B1: BVX Year | C1: Bank Eq. 30% decline | D1: Narrative Crisis | E1: Panic | F1: Panic month | G1: Widespread bank failures | H1: PANIC BANKING CRISIS | I1: BANK EQUITY CRISIS | J1: BVX list: UNION OF TWO TYPES | K1: Bank failures | L1: Sources Bank failures | M1: Documentation of Panic indicator & Panic month | N1: Other historical background & sources
A2: Argentina | B2: 1885 | C2: 0 | D2: 1 | E2: 0 | G2: 0 | H2: 0 | I2: 0 | J2: 0 | M2: Bordo and Eichengreen (1999) consider this a currency crisis but not a banking crisis. Reinhart & Rogoff (2014) no longer consider this a banking crisis in their 2014 update. There is no evidence of bank runs. | N2: Della Paolera & Taylor (2001, pp. 37-64) report that by 1884 banks suspended convertibility of notes for specie. A short period of currency volatility ensued that did not seem to have had substantial real effects.
A3: Argentina | B3: 1891 | C3: 1 | D3: 1890 | E3: 1 | F3: March 1890 | G3: 1 | H3: 1 | I3: 1 | J3: 1 | K3: Banco Nacional, Italian Bank of the River Plate, Banco de la Provincia de BA, Banco Hipotecario Nacional | L3: Cachanosky (2012) Hodge (1970) | M3: Triner & Wandschneider (2005, p. 207) say that the panic was in March 1890 when bank runs occured. Cachanosky (2012) report multiple depositor runs and bank failures. Reinhart & Rogoff (2014) date the beginning of the panic to July 1890 (but they seem to have misread Triner & Wandschneider, 2005, which is their source). | N3: Della Paolera & Taylor (2001, pp. 37-64) report that in 1890 Argentina was heavily indebted and became unable to roll over existing debt, most of which was repayble in gold only. A severe sovereign debt crisis ensued. In the first quarter of 1890, the Banco de la Provincia and the Banco Nacional were hit by a run that finally triggered the crisis (Cachanosky, 2012). In 1891, the Italian Bank of the River Plate suffered severe runs and later failed. The River Plate Bank also suffered from a run, but received liquidity from Baron Rothschild (Hodge, 1970). Reinhart & Rogoff (2014) date the crisis to July 1890-1891,Della Paolera & Taylor (2001) say that the panic was in March 1891 (which might be a typo of the year). Triner & Wandschneider (2005, p. 207) date the panic to March 1890. Bordo and Eichengreen (1999) date the crisis the 1889-1890.
A4: Argentina | B4: 1914 | C4: 1 | D4: 1 | E4: 1 | F4: July 1914 | G4: 0 | H4: 1 | I4: 0 | J4: 1 | K4: Banco Frances failed in August 1914, but this seems to be the only outright failure. | L4: Lough (1915) | M4: The outbreak of the war in the end of July 1914 was accompanied by a dramatic flight to liquidty around the globe. Many Argentine banks faced severe pressures as international depositors demanded liquidity. "Total deposits at Argentine banks fell by nearly 20 percent. The brunt of the hardship fell on the private banks, which lost over 45 percent of their deposits." (Nakamura and Zarazaga, 2001, pp. 25-26). | N4: The crisis was precipitated by a land price boom which was fueled by heavy speculation and private indebtedness. Large amounts of credit were extended by European banks. Banco Frances failed in August 1914. (Lough, 1915). In 1912, depositors started to withdraw up to 20% of total deposits from banks in reponse to real economic disturbances (Nakamura and Zarazaga, 2001). Della Paolera and Taylor (2001) name this crisis "the worst recession in Argentine history" (p. 190).
A5: Argentina | B5: 1930 | C5: 1 | D5: 1931 | E5: 1 | F5: April 1931 | G5: 0 | H5: 1 | I5: 0 | J5: 1 | K5: There is no evidence of widespread bank failures | M5: Bernanke and James (1991), Bordo and Eichengreen (1999), Bordo et al. (2001), Reinhart and Rogoff (2009, 2014), and Conde (2010) all agree that this was a banking crisis, but we have no information either way whether that means there was a panic. However, we include it as a panic to be conservative (but more research needs to be done). Bernanke and James (1991) date the crisis to April 1931. | N5: Bernanke and James (1991), Bordo and Eichengreen (1999), Bordo et al. (2001), Reinhart and Rogoff (2009, 2014), and Conde (2010) all agree that this was a banking crisis. Argentina left the gold standard in 1929 but the debt overhang from the 1920s resulted in a build-up of insolvent bank loans. The collapse of commodity prices forced a generalized default of many farmers (Rocha & Solomou, 2015, appendix I). There is no narrative evidence of widespread bank failures (but detailed sources are hard to come by). Bernanke and James (1991) date the crisis to April 1931.
A6: Argentina | B6: 1934 | C6: 1 | D6: 1 | E6: 1 | F6: September 1934 | G6: 1 | H6: 1 | I6: 1 | J6: 1 | K6: Banco Espanol del Rio de la Plata, Banco el Hogar Argentina, Banco Argentina-Uruguayo, Ernesto Tornquist & Co. | L6: Bernanke & James (1991, p.53) | M6: Bernanke & James (1991) note that four banks were faced with a government-sponsored merger to resolve their problems. They date the panic to September 1934. Della Paolera & Taylor (2002) estimate that the government bailout included about 32 percent of the loans of the private banking system, suggesting that this was a systemic crisis. | N6: Della Paolera and Taylor (2002) write that the Argentine Great Depression was mild and short-lived by international standards (p. 190): Argentina established its central bank in 1935 to deal with the wave of financial distress in the private banking system. Bernanke and James (1991) date the crisis to September 1934. Bernanke and James (1991), Bordo et al. (2001), and Reinhart and Rogoff (2009) list this as a separate crisis from the 1931 event (Rocha & Solomou, 2015)
A7: Argentina | B7: 1980 | D7: 1 | E7: 1 | F7: March 1980 | G7: 1 | H7: 1 | I7: 1 | J7: 1 | K7: Banco de Intercambio Regional, Banco de los Andes, Banco Oddone, Banco International, and at least 64 more. | L7: Montanaro (1990) says that by 1982 86 financial institutions had failed. Caprio and Klingebiel (1996) state that more than 70 institutions were liquidated. | M7: Montanaro (1990) citing Feldman (1983) says that this financial crisis reached panic proportions in Argentina in March 1980. This is confirmed by Laeven & Valencia (2018). | N7: The crisis followed a wave of deregulation in the late 1970’s after a military government seized power in 1976. Other economic problems include high foreign debts and run-away inflation rates. Montanaro (1990) writes: "The financial crisis in Argentina exploded in March 1980 with the failure of the country’s main private bank, the Banco de Intercambio Regional. By the middle of 1982, 86 banks and financial institutions had failed, amongst which were the Banco de los Andes, the Banco Oddone and the Banco International, the third, seventh and ninth banks respectively in the country." The author cites Feldman (1983). Caprio and Klingebiel (1996) state that more than 70 institutions were liquidated. Reinhart & Rogoff (2009), citing Kaminsky and Reinhart (1996), say that failure of the large private bank Banco de Intercambio Regional led to runs on three other banks in March 1980. The month is confirmed by Laeven & Valencia (2018).
A8: Argentina | B8: 1985 | D8: 1 | E8: 1 | F8: May 1985 | G8: 1 | H8: 1 | I8: 1 | J8: 1 | K8: Banco de Italia y Rio de la Plata and at least 7 more. | L8: Chavez (1985) | M8: Hyperinflation caused major banking distress and a run on banks forcing the Argentine central bank to close several banks in May 1985 (Chavez, 1985). The panic month is confirmed by Kaminsky & Reinhart (1999). | N8: In the first half of the 1980s there was an inflation and public debt crisis that forced the government in 1985 to take drastic reform measures known as the "Plan Austral". In late 1983, Argentina received IMF loans but these were halted in March 1985 when Argentina was out of compliance with several economic targets (CIA, 1985). The resulting economic turbulence and hyperinflation caused major banking distress and a run on banks forcing the Argentine central bank to close several banks in May 1985. Subsequently, dollar deposits were frozen for 120 days (Chavez, 1985). Reinhart & Rogoff (2014) strangely no longer consider this a banking crisis in their 2014 update. Their original source was Kaminsky & Reinhart (1999), who date the crisis to 1989.
A9: Argentina | B9: 1989 | D9: 1 | E9: 1 | F9: April 1989 | G9: 1 | H9: 1 | I9: 1 | J9: 1 | K9: Failed banks held 40 percent of financial system assets. | L9: Caprio & Klingebiel (2003, p. 7) | M9: Laeven & Valencia (2018) say this was a banking crisis and date the panic to December 1989 when deposits were freezed (though it's probable that this date is too late, as bank runs likely occurred earlier. Kaminsky & Reinhart (1999) date the crisis to April 1989; however, it's not clear whether this date refers to panics, but we assume so to pick the earliest possible date to be conservative (though more research needs to be done). | N9: Stabilization policies caused a public debt crisis and hyperinflation that resulted in major bank distress (Beckerman, 1995). As a result, "nonperforming assets accounted for 27 percent of the aggregate portfolio and 37 percent of the portfolios of state banks. Failed banks held 40 percent of financial system assets" (Caprio & Klingebiel, 2003, p. 7). Laeven & Valencia (2018) also say that this is a banking crisis.
A10: Argentina | B10: 1995 | C10: 1 | D10: 1 | E10: 1 | F10: December 1994 | G10: 1 | H10: 1 | I10: 1 | J10: 1 | K10: At least 40 banks failed (almost one third of total banks). | L10: Jacome (2008, p. 27) Caprio & Klingebiel (2003, p. 7) | M10: "The end-1994 Mexican devaluation triggered a wave of uncertainty on the sustainability of the currency board in Argentina, leading to widespread deposit runs and large capital outflows. As a result, from end-December to January 1995, peso deposits fell more than 15 percent." (Jacome, 2008, p. 27). Laeven & Valencia (2018) date the beginning of the panic a little bit later to January 1995. | N10: Jacome (2008) continues: "From December 1994 to late 1996, about 40 small and medium-size banks failed or were acquired or merged (almost one third of total banks). To cope with the instability created by the “Tequila” shock, the Argentine government passed a law in May 1995 that allowed the central bank to get involved in the resolution of distressed banks" (p. 27). Caprio & Klingebiel (2003) say that "eight banks [were] suspended and three banks collapsed. Through the end of 1997, 63 of 205 banking institutions were closed or merged" (p. 7).
A11: Argentina | B11: 2000 | C11: 1 | D11: 2001 | E11: 1 | F11: March 2001 | G11: 1 | H11: 1 | I11: 1 | J11: 1 | K11: Bank resolutions were applied to three foreign banks that exited the market. (Need to find names of failed banks, likely many.) | L11: Jacome (2008, p. 42) | M11: "12 private and public banks (40% of deposits) received liquidity assistance" (Jacome et al., 2011, p. 27). Laeven & Valencia (2018) report this as a banking crisis with deposit freezes which indicates panic behavior. Caprio & Klingebiel (2003, p. 7) report that the first bank run occured in March 2001. | N11: Jacome et al. (2011): "In 2002 the value of the U.S. dollar quadrupled with respect to the peso as the country exited the currency board. Self-fulfilling expectations of a large currency depreciation turned into a speculative attack against the domestic currency and, hence, the central bank was forced to abandon the peg before international reserves were exhausted, thereby triggering a balance of payments crisis." Jacome (2008) report that "12 private and public banks (40% of deposits) received liquidity assistance, and bank resolution was applied to three foreign banks that exited the market." (p. 42). Laeven and Valencia (2018) date the crisis to November 2001 with deposit freezes starting in December 2001.
A12: Argentina | B12: 2008 | C12: 1 | E12: 0 | G12: 0 | H12: 0 | I12: 0 | J12: 0 | M12: Boonman, Jacobs, & Kuper (2011) acknowledge that in 2008 Latin American currencies depreciated sharply versus the US dollar but that this did not cause a banking crisis in Argentina. This is line with the general consensus in the literature that Latin American banks were largely spared from the Global Financial Crisis (e.g. Lane & Milesi-Ferretti, 2011).
A13: Argentina | B13: 2011 | C13: 1 | E13: 0 | G13: 0 | H13: 0 | I13: 0 | J13: 0 | M13: There is no evidence of a banking panic. | N13: There is no inidcation of any distress in the banking system during and around the year of 2011 in Argentina. The bank equity decline is probably related to the public debt restructuring process that started in 2005 and briefly raised concerns again in 2011 and 2012.
A14: Australia | B14: 1893 | C14: 1 | D14: 1 | E14: 1 | F14: April 1893 | G14: 1 | H14: 1 | I14: 1 | J14: 1 | K14: "Widespread failures were evident among the land banks and building societies through 1891 and 1892 and intensified the fears of trading bank depositors". "Thirteen of Australia’s twenty-two trading banks [had] suspended operations" and subsequently restructured. Mercantile Bank of Australia, Federal Bank of Australia, and Queensland National Bank failed. | L14: Merrett (2013, p. 410-412); Bordo & Eichengreen (1999, p. 40) | M14: Fisher & Kent (1999, p. 11) say that "the banking panic started in earnest with the suspension of payment by the Commercial Bank of Australia in April" of 1893. As a source they refer to Merrett (1989). | N14: Bordo & Eichengreen (1999) say that "this crisis reflected a domestic lending boom, as a result of which the quality of bank assets deteriorated significantly, and stringency on global credit markets reflecting the fallout from the Baring Crisis" (p. 40). Intermediaries became highly leveraged and commodity prices decreased which in turn lead to borrower defaults. This subsequently led to stress in the banking system. (Merrett, 2013).
A15: Australia | B15: 1931 | C15: 0 | D15: 1 | E15: 1 | F15: April 1931 | G15: 0 | H15: 1 | I15: 0 | J15: 1 | K15: The (small) Government Savings Bank of New South Wales failed. Fisher and Kent (1999) say that only three banks failed during the 1929-1931 depression, and two banks merged with other banks due to their perilious financial situation, but these were all small banks | L15: Sunday Herald (1953), 26 April, p. 10 and Polden (1972). | M15: Fitzgibbon and Gizycki (2001, pp. 39-40) say that a balance of payment crisis caused several banks to face deposit runs. | N15: Fitzgibbon and Gizycki (2001, pp. 39-40) say that "the depression was ushered in by the drying up of overseas loans to Australia and a sharp fall in export prices. Australia’s terms of trade fell dramatically, causing a balance of payments crisis in 1929." However, the depression was not as severe as the crisis of the 1890’s. Reinhart & Rogoff (2009, 2014) do not consider this a systemic banking crisis in their 2009 version but do so in their 2014 update.
A16: Australia | B16: 1952 | C16: 1 | E16: 0 | G16: 0 | H16: 0 | I16: 0 | J16: 0 | M16: Reinhart & Rogoff (2014) record a stock market collapse but no crisis. There is no evidence of a banking panic.
A17: Australia | B17: 1974 | C17: 1 | E17: 0 | G17: 0 | H17: 0 | I17: 0 | J17: 0 | M17: Reinhart & Rogoff (2014) record a stock market collapse but no crisis. There is no evidence of a panic among banks. | N17: There was a large boom in property lending by banks and, especially, by non-bank property lenders. After interest rates soared, and financial conditions deteriorated, property prices declined and many property lenders faced liquidity problems. Reinhart & Rogoff (2014) record a stock market collapse but not other crises. Although there was stress in the banking system there is no further indication in the literature for a banking crisis (in the strict sense of a "bank") in or around 1974.
A18: Australia | B18: 1989 | C18: 0 | D18: 1 | E18: 1 | F18: March 1990 | G18: 1 | H18: 1 | I18: 0 | J18: 1 | K18: State Bank of Victoria, State Bank of South Australia | L18: Fitzgibbon and Gizycki (2001, pp. 62-66) | M18: "The banking industry experienced its worst losses since the 1890s. [...] The State Bank of Victoria and the State Bank of South Australia suffered large losses, and state governments provided significant capital injections in the resolution of these problems. [..] There were runs [only] on numerous non-bank institutions [...]. Various banks began to suffer large depositor withdrawals, but the Reserve Bank made statements declaring its belief that the banks were generally safe and that it was willing to intervene to provide liquidity" and deposit guarantees, which effectively stopped the runs (Fitzgibbon and Gizycki, 2001, pp. 62-66). | N18: Fitzgibbon and Gizycki (2001, pp. 62-66) say that "In 1989, the combination of high interest rates and a softening in the commercial property market brought broadly based credit quality problems to light." Reinhart & Rogoff (2009, 2014) consider this a systemic banking crisis in their 2009 version but a non-systemic crisis in their 2014 update. Jordà, Schularick, & Taylor (2017) consider this a systemic banking crisis.
A19: Australia | B19: 2008 | C19: 1 | E19: 0 | G19: 0 | H19: 0 | I19: 0 | J19: 0 | M19: Except for Romer & Romer (2017) who report slightly elevated financial distress there is no evidence for a banking crisis in Australia during the Global Financial Crisis. This is in line with narrative accounts like Kennedy (2009).
A20: Austria | B20: 1873 | C20: 1 | D20: 1 | E20: 1 | F20: May 1873 | G20: 1 | H20: 1 | I20: 1 | J20: 1 | K20: "The number of banks and banking firms dropped from 141 in 1873 to 45 in 1878." Depening on the source, up to 100 banks failed or disappeared. | L20: Willis & Beckhart (1929, p. 108) For a comprehensive list of failed banks see Rieder (2017, ch. 1, Table 1.19) | M20: This is the well-known Gründerkrach banking crisis. Reinhart & Rogoff (2009) date it to May 1873. Rieder (2017, ch. 1) reports massive depositor withdrawals and bank runs.
A21: Austria | B21: 1888 | C21: 1 | E21: 0 | G21: 0 | H21: 0 | I21: 0 | J21: 0 | M21: There is no evidence of a banking panic.
A22: Austria | B22: 1920 | C22: 1 | E22: 0 | G22: 0 | H22: 0 | I22: 0 | J22: 0 | M22: There is no evidence of a banking panic.
A23: Austria | B23: 1924 | C23: 1 | D23: 1 | E23: 0 | G23: 1 | H23: 0 | I23: 1 | J23: 1 | K23: Allgemeine Depositenbank was liquidated in July 1924. Also, the Austro-Polnische Bank, the Austro-Orientbank, as well as the private Union Bank failed. Later, in 1927, Unionbank and Verkehrsbank failed and were merged with Creditanstalt. Biedermannbank failed in 1927. In 1924 the number of joint stock banks in Vienna dropped from 66 to 36. | L23: Bernanke & James (1991, p. 51) Kindleberger (1984) Macher (2018) (Schubert, 1992, p. 8) | M23: Allgemeine Depositenbank ran into difficulty in May 1924 due to speculation on the French franc, which caused it to go into liquidation after suffering heavy withdrawals. About 40,000 savers lost a part of their deposits. However, this seems to be the only run: all the other banks were either received deposit guarantees or were absorbed. in 1926, two important banks (Centralbank der deutschen Sparkassen and Postal Savings Bank) suffered heavy losses, but the government guaranteed deposits to avoid a panic. Other banks that suffered losses were mostly absorbed by Creditanstalt (Schubert, 1992, p. 8). | N23: Reinhart & Rogoff (2009, 2014) report this as a systemic banking crisis. The four major universal banks of Austria came under increasing distress (Macher, 2018). Following the end of the hyperinflation and stabilization of the currency, there was a stock market boom followed then by a stock market crash in 1924 that preceded the banking difficulties. (Schubert, 1992, p. 8).
A24: Austria | B24: 1931 | C24: 1 | D24: 1929, 1931 | E24: 1 | F24: May 1931 | G24: 1 | H24: 1 | I24: 1 | J24: 1 | K24: Bodencreditanstalt, the second largest bank, fails in 1929 and is merged with Creditanstalt. The largest bank Creditanstalt failed on May 11, 1931. | L24: Bernanke & James (1991, p. 51) Macher (2018) | M24: Macher (2018) report large-scale deposit withdrawal and financial stress in 1931. The failure of Creditanstalt in May 1931 usheres in a full-blown banking panic. | N24: Reinhart & Rogoff (2009, 2014) report 1929 and 1931 as systemic banking crises. Bodencreditanstalt encountered serious liquidity problems in October 1929, but this is not considered a panic because: the bank could "meet these demands by taking (excessive) recourse to the discount window of the Austrian National Bank", and eventually the government arranged a merger with a strong partner, Creditanstalt (Schubert, 1992, p. 8).
A25: Austria | B25: 1966 | C25: 1 | E25: 0 | G25: 0 | H25: 0 | I25: 0 | J25: 0 | M25: There is no evidence of a banking panic.
A26: Austria | B26: 1982 | C26: 1 | E26: 0 | G26: 0 | H26: 0 | I26: 0 | J26: 0 | M26: There is no evidence of a banking panic. Lo Duca et al. (2017) confirm that there was only a limited effect on the Austrian banking system due to an external shock from global monetary policy.
A27: Austria | B27: 1995 | C27: 1 | E27: 0 | G27: 0 | H27: 0 | I27: 0 | J27: 0 | M27: There is no evidence of a banking panic.
A28: Austria | B28: 2008 | C28: 1 | D28: 1 | E28: 1 | F28: September 2008 | G28: 1 | H28: 1 | I28: 1 | J28: 1 | K28: Kommunalkredit Austria was nationalized in 2008. Constantia Privatbank failed in 2008 and was rescued by private banks. Hypo Alpe Adria was nationalized in 2009 and later liquidated. Volksbank receives capital support from the government in 2009 and is later liquidated. | L28: Lo Duca et al. (2017) Die Presse (2008) Die Presse (2009) Atkins (2016) | M28: Laeven & Valencia (2018), Reinhart & Rogoff (2014), and Romer & Romer (2017) agree that this was a systemic banking crisis. As with many European economies, Laeven & Valencia (2018) date the beginning of the panic to September 2008 when Lehman Brothers collapsed.
A29: Austria | B29: 2011 | C29: 1 | E29: 0 | G29: 1 | H29: 0 | I29: 1 | J29: 1 | K29: Volksbank again suffered large losses in 2011, was part-nationalized in 2011 by means of a debt-equity conversion of 250M EUR, and in October 2014, expecting failure of the ECB/EBA stress tests, was split up and restructed. A second bank, Hypo Alpe Adria, was part-nationalized due to European sovereign debt losses and split into a "good bank" and "bad bank" in 2014. Pfandbriefbank Oesterreich had to be rescued in 2015 by its regional bank owners. | M29: Reinhart & Rogoff (2014) report all years from 2008 through 2011 as a systemic bank crisis. Volksbank suffered losses from Greek debt defaults and other sources (Copolla, 2015). Romer & Romer (2017) report elevated stress in the banking system starting in the second half of 2011.
A30: Belgium | B30: 1870 | C30: 0 | D30: 1 | E30: 1 | F30: July 1870 | G30: 0 | H30: 1 | I30: 0 | J30: 1 | K30: There is no evidence of widespread bank failures. | M30: The evacuation of gold reserves from the capital sparked a panic in July 1870 and people demanded their notes to be exchanged for coins (Buyst & Maes, 2007, p. 17). Also, Reinhart & Rogoff (2007, 2014) date the beginning of this systemic banking crisis to July 1870.
A31: Belgium | B31: 1876 | C31: 1 | E31: 1 | F31: March 1876 | G31: 1 | H31: 1 | I31: 1 | J31: 1 | K31: Major bank Banque de Belgique failed in 1876 and was finally liquidated later in 1885. Banque de Bruxelles and Banque Central Anversoise had to be re-organized. | L31: Cameron & Bovykin (1991, p. 121) Buyst & Maes (2007, p. 24) Grossman (2010, p. 299) | M31: Buyst & Maes (2007, p. 22, 24) consider this a major banking crisis and date its beginning to March 1876 when Banque de Belgique failed. No direct evidence of a panic, but likely, so we mark it to be conservative.
A32: Belgium | B32: 1883 | C32: 0 | D32: 1885 | E32: 1 | F32: Could not be dated | G32: 1 | H32: 1 | I32: 0 | J32: 1 | K32: Third-largest bank Banque des Travaux Publics failed in 1885. Other smaller banks seemed to have failed, as well. | L32: Buyst & Maes (2008b, p. 169-170) | M32: Buyst & Maes (2008b, p. 169-170) record 1885-1886 as a separate banking panic with several bank failures. No direct evidence of a panic, but likely, so we mark it to be conservative.
A33: Belgium | B33: 1914 | D33: 1 | E33: 1 | F33: July 1914 | G33: 1 | H33: 1 | I33: 1 | J33: 1 | K33: Banque de Reports, de Fonds Publiques et de Dépôts d’Anvers were rescued and acquired by Société Générale. | L33: Buyst & Maes (2008b, p. 169-171) | M33: Reinhart & Rogoff (2009, 2014) date this systemic banking crisis to July 1914 when the war broke out. Panic withdrawals and suspension of bank note convertibility (Grossman, 2010, p. 300).
A34: Belgium | B34: 1925 | C34: 0 | D34: 1 | E34: 0 | G34: 0 | H34: 0 | I34: 0 | J34: 0 | K34: There is no evidence of widespread bank failures. | M34: Reinhart & Rogoff (2009, 2014) consider this a systemic banking crisis. After a close reading of their sources, however, no evidence for widespread distress or panic could be found. The authors cite Johnson (1997) who in turn refer to a "funding crisis" in Makinen and Woodward (1990). But "funding crisis" refers to, in the original article, the inability of governments and nonfinancial firms to rollover their debt, not a banking funding crisis.
A35: Belgium | B35: 1929 | C35: 1 | D35: 1931, 1934 | E35: 1 | F35: May 1931 | G35: 1 | H35: 1 | I35: 1 | J35: 1 | K35: Mid-sized Banque Chaudoir failed in 1930. Banque Belge de Travail and Algemeene Bankvereeniging failed in 1934. | L35: Buyst & Maes (2008a) Bernanke & James (1991, p. 52 | M35: Rumors about imminent failure of Banque de Bruxelles (second largest bank) induced withdrawals from all banks, especially from foreign depositors (Bernanke & James, 1991, p. 52). Reinhart & Rogoff (2009) follow Bernanke & James (1991) and date the beginning of the panic to May 1931.
A36: Belgium | B36: 1939 | D36: 1 | E36: 1 | F36: December 1939 | G36: 1 | H36: 1 | I36: 1 | J36: 1 | K36: Credit Anversois | L36: Buyst & Maes (2008a, p. 19) | M36: Large capital outflows in December 1939 from Belgian banks resulted in a banking crisis (Reinhart & Rogoff, 2009, 2014).
A37: Belgium | B37: 1974 | C37: 1 | E37: 0 | G37: 0 | H37: 0 | I37: 0 | J37: 0 | M37: There is no evidence of a banking panic.
A38: Belgium | B38: 1980 | C38: 1 | E38: 0 | G38: 0 | H38: 0 | I38: 0 | J38: 0 | K38: Three small banks (Banque Copine, Banque Andes and Geoffrey's Bank) failed but there is no further evidence of widespread bank failures. | L38: Gup (1998, Table 4.1) | M38: There is no evidence of a banking panic.
A39: Belgium | B39: 2002 | C39: 1 | E39: 0 | G39: 0 | H39: 0 | I39: 0 | J39: 0 | M39: There is no evidence of a banking panic.
A40: Belgium | B40: 2008 | C40: 1 | D40: 1 | E40: 1 | F40: September 2008 | G40: 1 | H40: 1 | I40: 1 | J40: 1 | K40: Fortis, then the largest financial-services firm, was nationalized. Dexia was rescued by several governments and later liquidated. | L40: van der Starre & Louis (2008) BBC News (2008) | M40: Laeven & Valencia (2018), Reinhart & Rogoff (2014), and Romer & Romer (2017) agree that this was a systemic banking crisis. As with many European economies, Laeven & Valencia (2018) date the beginning of the panic to September 2008 when Lehman Brothers collapsed.
A41: Belgium | B41: 2011 | C41: 1 | E41: 0 | G41: 1 | H41: 0 | I41: 1 | J41: 1 | K41: Major Franco-Belgian bank Dexia failed and received bail-out funds (again) from three governments in 2011. | L41: BBC News (2008) | M41: Romer & Romer (2017) report slightly elevated stress in the banking system starting in the second half of 2011. Against the backdrop of the default in Greece, problems in the liquidation of Dexia reemerged.
A42: Brazil | B42: 1890 | C42: 0 | D42: 1 | E42: 1 | F42: December 1890 | G42: 1 | H42: 1 | I42: 0 | J42: 1 | K42: 58 banks failed between 1891 and 1905 | L42: Triner (2014, p. 158) | M42: Infla Briones & Villela (2006), quoting Triner (2000, p. 47) report that inflationary chaos and an exchange-rate collapse caused large-scale bank failures with demand deposits dropping by more than 50%. Reinhart & Rogoff (2009) date the beginning of the panic to December 1890, though Triner (2001) reports February 1891. To be safe, we date the beginning of the panic to November 1890 when the London crisis and the Argentine default occured.
A43: Brazil | B43: 1897 | C43: 0 | D43: 1 | E43: 0 | G43: 0 | H43: 0 | I43: 0 | J43: 0 | M43: Civil war, deflation and currency depreciation, but no evidence of a banking panic (Reinhart & Rogoff, 2009; Triner, 2014; Briones & Villela, 2006).
A44: Brazil | B44: 1900 | C44: 0 | D44: 1 | E44: 1 | F44: October 1900 | G44: 1 | H44: 1 | I44: 0 | J44: 1 | K44: A second wave of bank failures (after the first one that started in 1891) occurred that resulted in a total of 58 failed banks between 1891 and 1905. | L44: Triner (2014, p. 158) | M44: Hanley (2005, pp. 172-182) and Reinhart & Rogoff (2009, 2014) both consider this a systemic banking crisis with massive deposit runs. Hanley (2005, p. 179) dates the panic to October 1900.
A45: Brazil | B45: 1914 | C45: 1 | D45: 1 | E45: 1 | F45: July 1914 | G45: 0 | H45: 1 | I45: 0 | J45: 1 | K45: There is no evdience of bank failures. | M45: Roberts (2013) and Reinhart & Rogoff (2009, 2014) argue this is a banking crisis. Roberts (2013, p. 215) dates the panic to July 1914 when deposit runs led to the closure of stock exchanges across countries in Latin America.
A46: Brazil | B46: 1923 | C46: 0 | D46: 1 | E46: 0 | G46: 0 | H46: 0 | I46: 0 | J46: 0 | K46: Reinhart & Rogoff (2009) report that the banking system contracted by 20%, citing Triner (2000). Triner (2000, p. 57), however, refers only to deposits and money supply. We cannot find evidence of any bank failures. | L46: Triner (2000, p. 57) | M46: Bordo et al. (2001) and Reinhart & Rogoff (2009, 2014) classify this as a banking crisis. Reinhart & Rogoff (2009, p. 353-356) report a severe monetary contraction due to Brazil's return to the Gold Standard. However, there is little evidence that there were bank runs or other elements that would qualify it as a panic.
A47: Brazil | B47: 1926 | C47: 0 | D47: 1 | E47: 0 | G47: 0 | H47: 0 | I47: 0 | J47: 0 | M47: Reinhart & Rogoff (2014) refer to this period as a non-systemic banking crisis but do not do so in their 2009 book. Banco de Brasil was affected by deflationary policies (Triner, 2000, p. 59). There is no further evidence indicating a systemic banking crisis or a panic.
A48: Brazil | B48: 1929 | C48: 0 | D48: 1 | E48: 1 | F48: June 1932 | G48: 0 | H48: 1 | I48: 0 | J48: 1 | K48: There is no evidence of widespread bank failures. | M48: Reinhart & Rogoff (2014) refer to this period as a non-systemic banking crisis but do not do so in their 2009 book. Triner (2000, p.59) state that the depression was comparatively mild in Brazil. But by 1932, stress in the banking sector had reached levels that had not been observed since 1891. In June 1932, the government created an emergency fund to meet withdrawals of deposits, suggesting a panic (League of Nations, 1935, p. 163).
A49: Brazil | B49: 1953 | C49: 1 | E49: 0 | G49: 0 | H49: 0 | I49: 0 | J49: 0 | M49: There is no evidence of a banking panic.
A50: Brazil | B50: 1957 | C50: 1 | E50: 0 | G50: 0 | H50: 0 | I50: 0 | J50: 0 | M50: There is no evidence of a banking panic.
A51: Brazil | B51: 1962 | D51: 1963 | E51: 0 | G51: 0 | H51: 0 | I51: 0 | J51: 0 | M51: There is no evidence of a banking panic. Reinhart & Rogoff (2009, 2014) follow Bordo et al. (2001) and report 1963 as a systemic banking crisis. There is, however, to the best of our knowledge, no credible evidence that there was in fact a banking crisis or a panic.
A52: Brazil | B52: 1985 | D52: 1 | E52: 1 | F52: September 1985 | G52: 1 | H52: 1 | I52: 1 | J52: 1 | K52: Brazilinvest was closed by the government. Large banks Comind, Maison Nave, and Auxiliar were nationalized. The National Housing Bank went bankrupt in 1986. | L52: Reinhart & Rogoff (2009, p. 354) Chwieroth & Walter (2019, pp. 457-460) | M52: Reinhart & Rogoff (2009, 2014) considers this a systemic banking crisis and date the start as September 1985. Kaminsky & Reinhart (1999, p. 478) date the beginning of the panic to September 1985. Chwieroth & Walter (2019) report that first bank failures occurred as early as February 1985.
A53: Brazil | B53: 1990 | D53: 1 | E53: 1 | F53: February 1990 | G53: 0 | H53: 1 | I53: 0 | J53: 1 | K53: There is no evidence of widespread bank failures. | M53: Reinhart & Rogoff (2009, 2014) report this as a systemic banking crisis. Laeven & Valencia (2018) refer to this as a borderline case. The latter date the start of the crisis to February 1990 and further report deposit freezes in March, likely indicating a panic.
A54: Brazil | B54: 1994 | D54: 1 | E54: 1 | F54: July 1994 | G54: 1 | H54: 1 | I54: 1 | J54: 1 | K54: 17 small banks were liquidated and the government put 43 financial institutions under adminstration or intervention. | L54: Reinhart & Rogoff (2009, p. 354) Jacome, Sedik & Townsend (2012, p. 27) | M54: Jacome (2008, p. 13) report this a systemic banking crisis, and so do Reinhart & Rogoff (2014) and Laeven & Valencia (2018). Reinhart & Rogoff date the beginning of the panic to July 1994, while Laeven & Valencia (2018) and Kaminsky & Reinhart (1999) indicate December.
A55: Brazil | B55: 1998 | C55: 1 | E55: 0 | G55: 0 | H55: 0 | I55: 0 | J55: 0 | M55: There is no evidence of a banking panic.
A56: Brazil | B56: 2008 | C56: 1 | E56: 0 | G56: 0 | H56: 0 | I56: 0 | J56: 0 | M56: Boonman, Jacobs, & Kuper (2011) acknowledge that in 2008 Latin American currencies depreciated sharply versus the US dollar but that this did not cause a banking crisis in Brazil. This is line with the general consensus in the literature that Latin American banks were largely spared from the Global Financial Crisis (e.g. Lane & Milesi-Ferretti, 2011).
A57: Brazil | B57: 2012 | C57: 1 | E57: 0 | G57: 0 | H57: 0 | I57: 0 | J57: 0 | M57: There is no evidence of a banking panic.
A58: Canada | B58: 1873 | C58: 0 | D58: 1 | E58: 1 | F58: July 1879 | G58: 1 | H58: 1 | I58: 0 | J58: 1 | K58: Bank of Acadia, Mechanics Bank, Consolidated Bank, Bank of Liverpool, and Banque Sainte Hyacinthe failed in 1873. Several other banks failed in the following years until 1879. This is a fairly large number of failures since there were no more than 36 banks reporting to the government during this period. | L58: Kryzanowski & Roberts (1993, p. 364) Willis and Beckhart (1929, pp. 327, 334-337) | M58: "In the strict sense of the word, Canada suffered no panic." (Breckenridge 1910, p. 114) [quoted by Grossman (2010)]. However, Ross (1922) provides evidence of widespread depositor runs: "had a meeting in Montreal with representatives of three Montreal banks, among which were the Bank of Montreal and the Merchants, but apparently nothing could be done to save the tottering institution. On the afternoon of Thursday, July 31, 1879, [Consolidated Bank] suspended payment. The failure was not a bad one, as it was able to pay its creditors, both noteholders and depositors, in full... On August 6, an uneasy feeling was observable in Hamilton and Sarnia with regard to the position of the Exchange Bank of Canada, the head office of which was in Montreal, and the following morning it suspended. Next day came the suspension of the Banque Ville Marie, 2 and rumours regarding the solvency of the Banque de St. Hyacinthe, the Banque de St. Jean and the Banque d'Hochelaga. To quote Mr. Anderson again: 'On the 9th [August] the run upon the City and District Savings Bank [Montreal] was serious, and the aggregate withdrawals of deposits were estimated at $500,000. There was also a run upon the Molson's Bank in Montreal, the Bank of Hamilton in Hamilton, and the Merchants Bank in Hamilton.' ...On Saturday afternoon the run on the City and District Savings Bank stopped. The Exchange Bank of Canada and the Banque Ville Marie were able to resume payment after the panic had subsided." | N58: Reinhart & Rogoff (2009, 2014) flag this as a systemic banking crisis. According to Grossman (2010), "Towards the end of the severe cyclical downturn ushered in by the commercial crisis of 1873, several banks failed or were liquidated… These accounted for about 7.5 per-cent of total bank capital at the time. According to McIvor (1958: 73), although the banks were criticized for reducing outstanding credit during this period, most banks survived by relying on their capital and reserves and by mergers."
A59: Canada | B59: 1906 | C59: 0 | D59: 1 | E59: 0 | G59: 0 | H59: 0 | I59: 0 | J59: 0 | K59: Ontario Bank failed in 1906. | M59: There is no banking panic. According to Carr, Mathewson, & Quigley (1995), "The assets and liabilities of the Ontario Bank were assumed by the Bank of Montreal in October 1906, with the other members of the CBA giving it a guarantee against ultimate loss. On 31 August 1908 the bank was formally placed in liquidation to facilitate the collection of the double liability, which proved more than sufficient to cover the deficiency in the assets."
A60: Canada | B60: 1907 | C60: 0 | D60: 1 | E60: 0 | G60: 1 | H60: 0 | I60: 0 | J60: 0 | K60: Sovereign Bank failed in 1907-1908. A few other small banks (e.g. St. Jean, St. Hyacinthe) failed or were absorbed, as well. | L60: Kryzanowski & Roberts (1993, p. 364) Carr, Mathewson & Quigley (1995, pp. 1139-1140) | M60: There was severe credit crunch in the Western provinces, a shortage of reserves due to the crisis in New York, but the few banks that did fail were all absorbed or assisted by other banks, and the government intervened to ease the credit crunch in the West. Rich (1989) writes this was the first time in Canadian history that the government assumed the role of lender of last resort by providing liquidity to troubled banks (Rich, 1989, p. 136). | N60: Reinhart & Rogoff (2014) report 1906 and 1907 as years of systemic banking crisis. Reinhart & Rogoff (2009) report 1908 as a separate banking crisis event, but do not do so anymore in their 2014 update.
A61: Canada | B61: 1912 | C61: 0 | D61: 1 | E61: 0 | G61: 0 | H61: 0 | I61: 0 | J61: 0 | K61: Bank of Vancouver fails in 1914, but this is the only failure. There were some mergers during this time, but Carr, Mathewson, and Quigley (1995) provide stock price and narrative evidence suggesting these mergers were done for strategic reasons and not because of bank weaknesses. | M61: Jamieson (1953, p. 46) writes: "Yet, although there was evidence of alarm here and there, including a few runs on the banks, on the whole reason prevailed, and nowhere in Canada was there anything approaching panic." Run on the Bank of Vancouver in October 1914 (Carr, Mathewson, & Quigley, 1995, pp. 1141-1142). he Bank of Vancouver, suspended payment on December 14, 1914. Jamieson (1954, p. 54) writes: "Though relatively it was a bad failure and depositors got very little, the absolute amounts were unimportant and repercussions purely local." | N61: Coincided with the bust of a real estate boom in Vancouver and the Western farm provinces.
A62: Canada | B62: 1920 | C62: 1 | D62: 1923 | E62: 1 | F62: December 1921 | G62: 1 | H62: 1 | I62: 1 | J62: 1 | K62: Major bank Home Bank of Canada failed in August 1923. Absorption of failing banks, such as Merchants Bank in 1922, Bank of Hamilton in 1923, Sterling Bank and Banque National in 1924, and Molson's Bank and Union Bank in 1925. | L62: Kryzanowski & Roberts (1993, p. 364) Carr, Mathewson & Quigley (1995, pp. 1142-1143) | M62: The banking system faced large difficulties with the result of sporadic bank runs and that "millions of deposits were withdrawn and it was not until the end of the year [1923] that the situation quietened" (Jamieson, 1953, p. 65). Some solvent banks, such as the Dominion and Imperial, experienced runs in 1924. Run on the small bank La Banque Nationale in December 1921 (Carr, Mathewson, & Quigley, 1995, pp. 1148-1149; Jamieson, 1953, p. 54). | N62: Reinhart & Rogoff (2009, 2014) consider 1923 a systemic banking crisis.
A63: Canada | B63: 1932 | C63: 1 | E63: 0 | G63: 0 | H63: 0 | I63: 0 | J63: 0 | K63: There is no evidence of widespread bank failures during the Great Depression in Canada. Only one small bank Weyburn Bank (an agricultural bank in rural Saskatchewan) was absorbed (by Imperial Bank in 1931) after significant financial difficulties. | M63: No evidence of panics, as documented by Kryzanowski & Roberts (1993). The Canadian government provided liquidity assistance to banks during the early 1930s. | N63: However, there were still deep losses at the banks. At the Bank of Montreal, over half of loans were non-performing in 1932-1936 (Kryzanowski & Roberts, 1993). Although no banks failed, many small trust companies and nonbank lenders failed (Colonial Investment & Loan Co.) or were absorbed (London Loan & Savings Co., People's Loan & Savings Co., Consolidated Trusts Co., Union Trust Co., Standard Trust Co.).
A64: Canada | B64: 1974 | C64: 1 | E64: 0 | G64: 0 | H64: 0 | I64: 0 | J64: 0 | M64: There is no evidence of a banking panic.
A65: Canada | B65: 1982 | C65: 0 | D65: 1 | E65: 1 | F65: July 1982 | G65: 1 | H65: 1 | I65: 0 | J65: 1 | K65: The Canadian Commercial Bank of Edmonton and the Northland Bank failed in 1985. Over 20 trust companies and mortgage corporations failed, as well. In 1986 the Bank of British Columbia had to be rescued and was bought by HSBC. Continental Bank was also liquidated. | L65: Bordo & Klingebiel (2003, p. 15) Gup (1998, p. 18-22) | M65: The failures of the two banks coincided with deposit runs. Mercantile Bank of Canada also suffered bank runs and was taken over National Bank. These were all wholesale funded banks. | N65: Reinhart & Rogoff (2014) and Bordo & Klingenbiel (2003) consider the years 1983-1985 a non-systemic banking crisis.
A66: Canada | B66: 2008 | C66: 1 | E66: 0 | G66: 0 | H66: 0 | I66: 0 | J66: 0 | M66: Canada did not experience a banking crisis during the Global Financial Crisis (Bordo, Redish & Rockoff, 2015).
A67: Chile | B67: 1878 | E67: 1 | F67: December 1877 | G67: 1 | H67: 1 | I67: 1 | J67: 1 | K67: Banco del Pobre, failed in 1877. Banco Alianza and Banco Consolidado failed in 1879. | L67: Briones (2002, Table 2, pp. 10-11) | M67: Briones (2002, 2007) call this a liquidity crisis of the banking system. Especially the Bank Nacional de Chile faced massive demand for note conversion to specie. Brock (2016) calls it a banking panic. Briones (2007) proposes that the panic started in December 1877. | N67: Briones & Villela (2006, p. 340) refer to it as a severe banking crisis. Reinhart & Rogoff (2009, 2014) do not even consider this a non-systemic banking crisis.
A68: Chile | B68: 1889 | C68: 0 | D68: 1 | E68: 0 | G68: 0 | H68: 0 | I68: 0 | J68: 0 | N68: Reinhart & Rogoff (2014) report 1890 as a systemic banking crisis but do not do so in their 2009 book. There is however, very little evidence that there was, indeed, a systemic banking crisis in or around that year. One of the few sources is Brock (2016) which suggests that this was rather a sudden stop crisis than a banking crisis. Bordo & Eichengreen (1999) call 1887 a currency crisis.
A69: Chile | B69: 1898 | C69: 0 | D69: 1 | E69: 1 | F69: July 1898 | G69: 1 | H69: 1 | I69: 0 | J69: 1 | K69: Banco de la Union failed in 1897. The 1880s and 1890s saw four more bank failures. | L69: Briones (2002, Table 2, pp. 10-11) | M69: Reinhart & Rogoff (2009) say this was a systemic banking crisis that started with a bank run in Santiago in July 1898. | N69: Bordo & Eichengreen (1999) call 1898 a twin crisis.
A70: Chile | B70: 1907 | D70: 1 | E70: 1 | F70: October 1907 | G70: 1 | H70: 1 | I70: 1 | J70: 1 | K70: The 7th biggest bank Banco Mobiliario and two other banks failed. | L70: Briones & Villela (2006, p. 8) | M70: Noyes (1909, p. 205) reports bank runs and "complete disorder in business circles", and further dates the outbreak of the panic to October 1907, almost simultaneously to the events in New York City. | N70: Reinhart & Rogoff (2009, 2014) say this was a systemic banking crisis. Bordo & Eichengreen (1999) call this only a currency crisis.
A71: Chile | B71: 1914 | D71: 1 | E71: 1 | F71: July 1914 | G71: 0 | H71: 1 | I71: 0 | J71: 1 | K71: Evidence of only one bank failing (Banco Italiano). Evidence seems to suggest that it was not a major bank. | L71: Roberts (2013, p. 216) | M71: Roberts (2013, p. 216-217) writes that "the bank runs were expressions of pure panic". Roberts (2013, p. 215) dates the panic to July 1914 when deposit runs led to the closure of stock exchanges across countries in Latin America. | N71: Reinhart & Rogoff (2014) say this was a systemic banking crisis but do not do so in their 2009 book.
A72: Chile | B72: 1925 | D72: 1 | E72: 1 | F72: December 1925 | G72: 1 | H72: 1 | I72: 1 | J72: 1 | K72: Second largest bank Banco Español de Chile failed and was restructured in 1925-1926. | L72: Carrasco (2009) | M72: The second largest bank Banco Español de Chile was liquidated in December 1925. No evidence either way specifically about panics, but likely that there was a panic based on circumstantial evidence (so we say it's a panic to be conservative). | N72: Reinhart & Rogoff (2014) say 1926 was a systemic banking crisis. They do not say so in their 2009 book.
A73: Chile | B73: 1931 | C73: 1 | E73: 1 | F73: June 1932 | G73: 1 | H73: 1 | I73: 1 | J73: 1 | K73: 4 out of 22 banks were forced to close in 1930 and 1931. | L73: Brock (1998, p. 15) | M73: In June 1932, the goverenment froze deposits and declared a three-day bank holiday, suggesting that there was a panic (Brock, 1998, p. 15). | N73: Reinhart & Rogoff (2014) consider this a debt, inflation, and currency crisis but not a systemic banking crisis.
A74: Chile | B74: 1954 | C74: 1 | E74: 0 | G74: 0 | H74: 0 | I74: 0 | J74: 0 | M74: There is no evidence of a banking panic.
A75: Chile | B75: 1962 | C75: 1 | E75: 0 | G75: 0 | H75: 0 | I75: 0 | J75: 0 | M75: There is no evidence of a banking panic. Drop in bank stock prices are probably due to a spike in inflation (up to 40%).
A76: Chile | B76: 1970 | C76: 1 | E76: 0 | G76: 0 | H76: 0 | I76: 0 | J76: 0 | M76: There is no evidence of a banking panic. The drop in bank stock prices may have to do with Allende's announcement to nationalize banks.
A77: Chile | B77: 1976 | C77: 0 | D77: 1 | E77: 1 | F77: June 1975 | G77: 1 | H77: 1 | I77: 0 | J77: 1 | K77: The entire SINAP system failed in 1976. The medium-sized bank Banco Osorno y La Union failed in 1977. A number of other finanical institutions failed, as well. | L77: Kaufman (1992, p. 73) | M77: In June 1975, after many depositors had fled the SINAP system, its deposits were freezed for 60 days (Kaufman, 1992, p. 76), indicating a panic. | N77: Reinhart & Rogoff (2009, 2014) say 1976 was a systemic banking crisis. Laeven & Valencia (2018) concur.
A78: Chile | B78: 1982 | C78: 1 | D78: 1980 | E78: 1 | F78: September 1981 | G78: 1 | H78: 1 | I78: 1 | J78: 1 | K78: Four banks failed in 1981, and seven banks failed in 1983. Those banks were taken over by the supervisory institution. Also, a number of other financial institutions failed. | L78: Caprio & Klingebiel (2003, p. 8) Kaufman (1992, pp. 78-83) | M78: Laeven & Valencia (2018) date the panic to November 1981. Kaminsky & Reinhart (1999) say it already started in September. | N78: Reinhart & Rogoff (2014) say 1981-1984 was a systemic banking crisis. Caprio & Klingebiel (2003, p. 8) report that "In 1981 the authorities intervened in four banks and four nonbank financial institutions accounting for 33 percent of outstanding loans. In 1983 the authorities intervened in seven banks and one financiera accounting for 45 percent of financial system assets. By the end of 1983, 19 percent of loans were nonperforming."
A79: Chile | B79: 1998 | C79: 1 | E79: 0 | G79: 0 | H79: 0 | I79: 0 | J79: 0 | M79: There is no evidence of a banking panic.
A80: Colombia | B80: 1931 | C80: 1 | E80: 1 | F80: June 1929 | G80: 0 | H80: 1 | I80: 0 | J80: 1 | K80: According to White (1997), only one bank failed, but 23 branches and agencies of banks and the Caja de Credito Agrario were closed. | M80: Bank deposits fell by more than 50% during 1929-1931, indicating a panic (Drake, 1989, p. 62). However, this seems to be mostly foreign outflows, as White (1997) reports that local depositor confidence was generally maintained. | N80: Reinhart & Rogoff (2009, 2014) do not report any banking crisis event. White (1997) reports that problems started after the coffee price boom ended in late 1928; although the system was technically solvent, enormous bank losses in 1931-33 were followed by a deep credit crunch. The period saw very high financial stress among banks, in addition to non-bank runs. The domestic banking system survived through a combination of forbearance, policy intervention, and prudent bank management. The consolidation of the banking sector in the first half of the 1920s had left it in a much stronger position when the Great Depression arrived in Colombia (White, 1998).
A81: Colombia | B81: 1972 | C81: 1 | E81: 0 | G81: 0 | H81: 0 | I81: 0 | J81: 0 | M81: There is no evidence of a banking panic.
A82: Colombia | B82: 1982 | C82: 1 | D82: 1 | E82: 0 | G82: 1 | H82: 0 | I82: 1 | J82: 1 | K82: Corporacion Financiera Cofinatura failed in 1980, and in 1982 three finance companies, the Fondo Ganadero de la Guajira, and four securities firms were taken over by the government. Many more banks were taken over through 1987. (White, 1997) | L82: Caprio & Klingebiel (2003, p. 8) | M82: There were no panics, as the Colombian government intervened in all failing companies, including extraordinary intervention to save the large and extremely illiquid Banco del Estado, to avert a panic (White, 1997). | N82: Reinhart & Rogoff (2009, 2014) and Laeven & Valencia (2018) say this was a systemic bank crisis. However, bank losses were extremely severe, with bad loans representing 12 of assets and 343 percent of capital by 1985 (White, 1997).
A83: Colombia | B83: 1998 | C83: 1 | D83: 1 | E83: 1 | F83: June 1998 | G83: 1 | H83: 1 | I83: 1 | J83: 1 | K83: 12 bank failures occured between June 1998 and December 2001, representing a failure rate of 31 percent. | L83: Gomez-Gonzalez & Kiefer (2009, p. 19). | M83: Laeven & Valencia (2018) date the panic to June 1998. This is confirmed by Gomez-Gonzalez & Kiefer (2009, p. 18). Reinhart & Rogoff (2009) report severe liquidity problems in the banking sector. | N83: Reinhart & Rogoff (2009, 2014) and Laeven & Valencia (2018) say this was a systemic bank crisis.
A84: Colombia | B84: 2008 | C84: 1 | E84: 0 | G84: 0 | H84: 0 | I84: 0 | J84: 0 | M84: Boonman, Jacobs, & Kuper (2011) acknowledge that in 2008 Latin American currencies depreciated sharply versus the US dollar but that this did not cause a banking crisis in Colombia. This is line with the general consensus in the literature that Latin American banks were largely spared from the Global Financial Crisis (e.g. Lane & Milesi-Ferretti, 2011).
A85: Czech Republic | B85: 1923 | E85: 1 | F85: May 1923 | G85: 1 | H85: 1 | I85: 1 | J85: 1 | K85: Moravsko Sleska Banka, the Bohemian Foreign Banking Corporation, and the Pozemkova Bank failed. | L85: Federal Reserve (1923, p. 920) | M85: The bank failures resulted in widespread deposit withdrawals from smaller banks across the country, indicating a panic (Federal Reserve, 1923). Federal Reserve (1923, p. 920) state that the financial difficulties of the three banks became public in May 1923, which serves as our start date of the panic.
A86: Czech Republic | B86: 1931 | C86: 0 | D86: 1 | E86: 0 | G86: 0 | H86: 0 | I86: 0 | J86: 0 | M86: Bernanke & James (1991) report that their were some deposit withdrawals but no panic. | N86: Reinhart & Rogoff (2009) consider this a systemic bank crisis but dropped the country from their 2014 update.
A87: Czech Republic | B87: 1991 | D87: 1 | E87: 1 | F87: April 1994 | G87: 1 | H87: 1 | I87: 1 | J87: 1 | K87: More than 20, mostly small banks failed. Banka Bohemia was the first to fail in 1994. | L87: Dubska (2013) | M87: The panic can be dated to April 1994 when Banka Bohemia faced a depositor run. Other bank runs ensued. | N87: Caprio & Klingebiel (2003) are the only source that date the beginning of the banking crisis of the 1990s to 1991. Lo Duca et al. (2017) and Laeven & Valencia (2018) record no crisis in or around this year.
A88: Czech Republic | B88: 1995 | C88: 1 | D88: 1996 | E88: 1 | F88: June 2000 | G88: 1 | H88: 1 | I88: 1 | J88: 1 | K88: In 2000, the third-largest bank Investiční a Poštovní banka failed. | L88: Caprio & Klingebiel (2003) Dubska (2013) | M88: Run on the third-largest bank Investiční a Poštovní Banka in 2000. | N88: Laeven & Valencia (2018) report this as a systemic banking crises. In 1994–1995, 38 percent of the banking system loans were nonperforming (Caprio & Klingebiel, 2003). Lo Duca et al. (2017) date the beginning of the crisis to May 1997.
A89: Denmark | B89: 1877 | C89: 0 | D89: 1 | E89: 1 | F89: Could not be dated | G89: 1 | H89: 1 | I89: 0 | J89: 1 | K89: Several savings banks and a few commercial banks (Den vestsjællandske Folkebank, Fyens Folkebank) were liquidated. | L89: Abildgren (2014, p. 23) Sumner et al. (1896, p. 386) | M89: Reinhart & Rogoff (2009, 2014) say this was a systemic banking crisis. Sumner et al. (1896, p. 386) provides evidence that there was severe stress in the banking system but no information on the exact dating of a panic could be found.
A90: Denmark | B90: 1885 | C90: 0 | D90: 1 | E90: 1 | F90: September 1885 | G90: 1 | H90: 1 | I90: 0 | J90: 1 | K90: Varde bank failed in 1885 largely due to fraud, and Handels- og Landmandsbanken, Nyborg was liquidated the same year. | L90: Abildgren (2014, p. 23) Frifelt (1947) | M90: Reinhart & Rogoff (2009, 2014) say this was a systemic banking crisis and that the National Bank intervened to provide support for banks, indicating a panic. Bankruptcies among non-financial firms caused the banking sector's liquidity to come under pressure (Abildgren, 2014, p. 23).
A91: Denmark | B91: 1902 | C91: 0 | D91: 1 | E91: 0 | G91: 0 | H91: 0 | I91: 0 | J91: 0 | N91: Reinhart & Rogoff (2009, 2014) say this was a systemic banking crisis. However, on close inspection of the sources provided (Conant, 1915, p. 300) and of other sources, one cannot find any substantial evidence, that there was a separate crisis event in 1902. The events described in Reinhart & Rogoff (2009, p. 359) can most likely be attributed to the crisis of 1907. The described failure of Freeholder's bank actually occured in 1908.
A92: Denmark | B92: 1907 | C92: 0 | D92: 1 | E92: 1 | F92: February 1908 | G92: 1 | H92: 1 | I92: 0 | J92: 1 | K92: Grundejerbank failed in 1908. The Detailhandler Bank's imminent failure prompted a bankout orchestrated by the Nationalbank. | L92: Conant (1915, p. 300) | M92: Reinhart & Rogoff (2009, 2014) and Bordo & Eichengreen (2009) say this was a systemic banking crisis. The failure of Grundejerbank (Freeholder's bank) in February 1908 was followed by a bank run on several institutions (Conant, 1915, p. 300).
A93: Denmark | B93: 1914 | D93: 1 | E93: 0 | G93: 0 | H93: 0 | I93: 0 | J93: 0 | K93: Several large commercial banks, including Scandinavia's largest bank – Landmandsbanken – received capital and/or liquidity support from the government and the Nationalbank. No failures were reported, however. | L93: Abildgren (2014, p. 23) | M93: The stock exchange closed to avert a panic and payment in specie was suspended when the war broke out in July 1914. Roberts (2013, p. 206), however, reports that, unlike many other countries in July 1914, there was "no kind of panic, in spite of the grave disturbance in banking" . | N93: Reinhart & Rogoff (2014) say this was a systemic banking crisis but do not do so in their 2009 book.
A94: Denmark | B94: 1919 | C94: 1 | D94: 1921 | E94: 1 | F94: September 1922 | G94: 1 | H94: 1 | I94: 1 | J94: 1 | K94: In 1922 a total of 23 banks had to be acquired, reconstructed, or liquidated. The largest bank, Landmandsbanken, was the most spectacular failure in September 1922, the fourth and fifth largest banks failed in 1924 and 1925, respectively, and in 1928 the third largest, Privatbanken, had to be rescued by private investors. In total, | L94: Hansen (2012, p. 679-680) | M94: The collapse of major bank Landmandsbanken in September 1922 triggered a panic and bank runs (Hansen, 2012). | N94: Reinhart & Rogoff (2009, 2014) say 1921 was a systemic banking crisis. It was caused by reckless lending during the war and a deflationary spiral in the early 20s, and lasted many years.
A95: Denmark | B95: 1931 | C95: 0 | D95: 1 | E95: 0 | G95: 0 | H95: 0 | I95: 0 | J95: 0 | K95: Reinhart & Rogoff (2009, 2014) say this was a systemic banking crisis. There is, however, no evidence of bank failures. | M95: Hansen (1995) report that central bank intervention prevented panics despite the liquidity problems in the banking sector.
A96: Denmark | B96: 1974 | C96: 1 | E96: 0 | G96: 0 | H96: 0 | I96: 0 | J96: 0 | M96: There is no evidence of a banking panic. Lo Duca et al. (2017) confirm that the financial system remained resilient to external stress factors.
A97: Denmark | B97: 1992 | C97: 1 | D97: 1987 | E97: 0 | G97: 1 | H97: 0 | I97: 1 | J97: 1 | K97: 9th largest bank Varde Bank had to be bailed-out in 1992-1993. Major bank failures include Krone Banken (1984), 6. Juli Bank and C&G Bank (1987), and Unibank (1992), and Baltica Bank and Himmerlandsbanken (1993). Overall, 52 mostly small and medium sized banks closed due to financial difficulties. | L97: Abildgren & Thomsen (2011, p. 127), (Abildgren, Monetary History of Denmark: 1980-1995) | M97: There is no narrative evidence of panics. The government and the Nationalbank were succesful in providing support to distressed banks (Lo Duca et al., 2017). The closest thing to a runs was, "on Friday June 19, 1992, several branches reported a large number of clients had withdrawn there money. However, Nationalbanken stepped in to provide liquidity guarantees to Unibank a through a stand-by liquidity facility. On Monday June 22, 1992 when Unibank branches it was clear an all-out bank run had been prevented, as the liquidity guarantee was credible. Therefore, a large scale run had been prevented." (Source: Ole Mikkelsen’s 2011 biography of Peter Straarup, former CEO of Danske Bank). | N97: Reinhart & Rogoff (2014) say that this was a non-systemic banking crisis which lasted from March 1987 to 1992. Lo Duca et al. (2017) date the beginning of the crisis to March 1987, as well. Laeven & Valencia (2018) do not consider this a systemic banking crisis.
A98: Denmark | B98: 2008 | C98: 1 | D98: 1 | E98: 1 | F98: September 2008 | G98: 1 | H98: 1 | I98: 1 | J98: 1 | K98: Between 2008 and 2013 around one-third of all banks in Denmark failed or ceased to exist. 11 banks dissappeared in 2008 and 8 in 2009. | L98: Abildgren (2014, p. 23) Rangvid et al. (2013, ch. 11, pp. 249-297) | M98: Laeven & Valencia (2018) date the beginning of the panic to September 2008. Denmark did not bail out most banks but instead followed a bail-in approach resulting in the disappearance of about on third of all banks in the country (Rangvid et al. 2013, ch. 11). | N98: Laeven & Valencia (2018), Reinhart & Rogoff (2014), and Lo Duca et al. (2017) say this was a systemic banking crisis.
A99: Denmark | B99: 2011 | C99: 1 | E99: 0 | G99: 1 | H99: 0 | I99: 1 | J99: 1 | K99: 11 banks dissappeared in 2010, 10 in 2011, 17 in 2012, and another 5 in 2013. | L99: Rangvid et al. (2013, ch. 11, pp. 249-297) | M99: Romer & Romer (2017) report elevated financial stress. There is no evidence of renewed panic. | N99: Reinhart & Rogoff (2014) attribute 2011 still to the previous crisis event, and so do Lo Duca et al. (2017).
A100: Egypt | B100: 1907 | C100: 0 | D100: 1 | E100: 1 | F100: May 1907 | G100: 1 | H100: 1 | I100: 0 | J100: 1 | K100: One important bank failed (Noyes 1909, p. 203), and Commercial, Industrial, & Land Co. of Egypt and Société immobilière d'Égypte also failed. Credit Franco-Egyptien was absorbed. Credit Foncier Egyptien failed and required a gold infusion from the Bank of England. | L100: Noyes (1909, p. 203) | M100: According to Noyes (1909, pp. 202-203) there was a depositor run in May 1907 that triggered a panic. | N100: Reinhart & Rogoff (2009, 2014) report this as a systemic banking crisis.
...
